{"nm":"Comp 11","ddd":0,"h":350,"w":350,"meta":{"g":"@lottiefiles/toolkit-js 0.33.2"},"layers":[{"ty":3,"nm":"NULL ","sr":1,"st":0,"op":125,"ip":0,"hd":false,"ddd":0,"bm":0,"hasMask":false,"ao":0,"ks":{"a":{"a":0,"k":[50,50,0],"ix":1},"s":{"a":0,"k":[100,100,100],"ix":6},"sk":{"a":0,"k":0},"p":{"a":0,"k":[175,175,0],"ix":2},"r":{"a":0,"k":0,"ix":10},"sa":{"a":0,"k":0},"o":{"a":0,"k":0,"ix":11}},"ef":[],"ind":1},{"ty":4,"nm":"Layer 6","sr":1,"st":5,"op":25,"ip":5,"hd":false,"ddd":0,"bm":0,"hasMask":false,"td":1,"ao":0,"ks":{"a":{"a":0,"k":[-48.876,71.657,0],"ix":1},"s":{"a":0,"k":[100,100,100],"ix":6},"sk":{"a":0,"k":0},"p":{"a":1,"k":[{"o":{"x":0.333,"y":0},"i":{"x":0.407,"y":1},"s":[-48.876,71.657,0],"t":8,"ti":[0,0,0],"to":[2.357,-2.357,0]},{"o":{"x":0.606,"y":0},"i":{"x":0.667,"y":1},"s":[-34.734,57.515,0],"t":18,"ti":[2.357,-2.357,0],"to":[0,0,0]},{"o":{"x":0.167,"y":0.167},"i":{"x":0.833,"y":0.833},"s":[-48.876,71.657,0],"t":28,"ti":[0,0,0],"to":[0,0,0]},{"o":{"x":0.167,"y":0.167},"i":{"x":0.833,"y":0.833},"s":[-48.876,71.657,0],"t":60,"ti":[0,0,0],"to":[6.246,2.711,0]},{"o":{"x":0.167,"y":0.167},"i":{"x":0.833,"y":1},"s":[-11.399,87.92,0],"t":65,"ti":[6.246,2.711,0],"to":[0,0,0]},{"s":[-48.876,71.657,0],"t":71}],"ix":2},"r":{"a":1,"k":[{"o":{"x":0.167,"y":0.167},"i":{"x":0.833,"y":0.833},"s":[0],"t":35},{"o":{"x":0.167,"y":0.167},"i":{"x":0.833,"y":0.833},"s":[-20],"t":40},{"o":{"x":0.167,"y":0.167},"i":{"x":0.833,"y":0.833},"s":[10],"t":45},{"o":{"x":0.167,"y":0.167},"i":{"x":0.833,"y":0.833},"s":[8],"t":50},{"o":{"x":0.167,"y":0.167},"i":{"x":0.833,"y":0.833},"s":[-14],"t":55},{"o":{"x":0.167,"y":0.167},"i":{"x":0.833,"y":0.833},"s":[24],"t":60},{"o":{"x":0.167,"y":0.167},"i":{"x":0.667,"y":1},"s":[27],"t":65},{"o":{"x":0.333,"y":0},"i":{"x":0.667,"y":1},"s":[0],"t":71},{"o":{"x":0.333,"y":0},"i":{"x":0.667,"y":1},"s":[30],"t":78},{"s":[0],"t":85}],"ix":10},"sa":{"a":0,"k":0},"o":{"a":0,"k":100,"ix":11}},"ef":[],"shapes":[{"ty":"gr","bm":0,"hd":false,"mn":"ADBE Vector Group","nm":"Group 1","ix":1,"cix":2,"np":2,"it":[{"ty":"sh","bm":0,"hd":false,"mn":"ADBE Vector Shape - Group","nm":"Path 1","ix":1,"d":1,"ks":{"a":0,"k":{"c":true,"i":[[-0.203,-1.399],[0,0],[-1.132,0.774],[0,0]],"o":[[0,0],[-0.199,-1.396],[0,0],[-1.136,0.771]],"v":[[-78.945,83.144],[-76.543,81.602],[-75.274,78.18],[-77.68,79.719]]},"ix":2}},{"ty":"fl","bm":0,"hd":false,"mn":"ADBE Vector Graphic - Fill","nm":"Fill 1","c":{"a":0,"k":[0.7255,0.7255,0.7255],"ix":4},"r":1,"o":{"a":0,"k":100,"ix":5}},{"ty":"tr","a":{"a":0,"k":[0,0],"ix":1},"s":{"a":0,"k":[100,100],"ix":3},"sk":{"a":0,"k":0,"ix":4},"p":{"a":0,"k":[0,0],"ix":2},"r":{"a":0,"k":0,"ix":6},"sa":{"a":0,"k":0,"ix":5},"o":{"a":0,"k":100,"ix":7}}]},{"ty":"gr","bm":0,"hd":false,"mn":"ADBE Vector Group","nm":"Group 2","ix":2,"cix":2,"np":2,"it":[{"ty":"sh","bm":0,"hd":false,"mn":"ADBE Vector Shape - Group","nm":"Path 1","ix":1,"d":1,"ks":{"a":0,"k":{"c":true,"i":[[0,0],[-0.199,-1.396],[0,0],[0,0],[-1.132,0.774]],"o":[[-1.139,0.776],[0,0],[0,0],[-0.199,-1.396],[0,0]],"v":[[-71.353,75.659],[-72.62,79.088],[-70.219,77.546],[-70.216,77.541],[-68.947,74.12]]},"ix":2}},{"ty":"fl","bm":0,"hd":false,"mn":"ADBE Vector Graphic - Fill","nm":"Fill 1","c":{"a":0,"k":[0.7255,0.7255,0.7255],"ix":4},"r":1,"o":{"a":0,"k":100,"ix":5}},{"ty":"tr","a":{"a":0,"k":[0,0],"ix":1},"s":{"a":0,"k":[100,100],"ix":3},"sk":{"a":0,"k":0,"ix":4},"p":{"a":0,"k":[0,0],"ix":2},"r":{"a":0,"k":0,"ix":6},"sa":{"a":0,"k":0,"ix":5},"o":{"a":0,"k":100,"ix":7}}]},{"ty":"gr","bm":0,"hd":false,"mn":"ADBE Vector Group","nm":"Group 3","ix":3,"cix":2,"np":2,"it":[{"ty":"sh","bm":0,"hd":false,"mn":"ADBE Vector Shape - Group","nm":"Path 1","ix":1,"d":1,"ks":{"a":0,"k":{"c":true,"i":[[0,0],[-0.203,-1.399],[0,0],[-1.132,0.774]],"o":[[-1.136,0.771],[0,0],[-0.196,-1.4],[0,0]],"v":[[-65.024,71.606],[-66.288,75.03],[-63.887,73.488],[-62.619,70.059]]},"ix":2}},{"ty":"fl","bm":0,"hd":false,"mn":"ADBE Vector Graphic - Fill","nm":"Fill 1","c":{"a":0,"k":[0.7255,0.7255,0.7255],"ix":4},"r":1,"o":{"a":0,"k":100,"ix":5}},{"ty":"tr","a":{"a":0,"k":[0,0],"ix":1},"s":{"a":0,"k":[100,100],"ix":3},"sk":{"a":0,"k":0,"ix":4},"p":{"a":0,"k":[0,0],"ix":2},"r":{"a":0,"k":0,"ix":6},"sa":{"a":0,"k":0,"ix":5},"o":{"a":0,"k":100,"ix":7}}]},{"ty":"gr","bm":0,"hd":false,"mn":"ADBE Vector Group","nm":"Group 4","ix":4,"cix":2,"np":2,"it":[{"ty":"sh","bm":0,"hd":false,"mn":"ADBE Vector Shape - Group","nm":"Path 1","ix":1,"d":1,"ks":{"a":0,"k":{"c":true,"i":[[-2.933,1.887],[-51.48,70.352],[-0.701,21.006],[0.059,1.648],[0.021,-0.693],[6.539,-8.943],[0,0],[1.549,4.612]],"o":[[0,0],[6.539,-8.943],[0.067,-2.006],[-0.006,0.651],[-0.701,21.006],[-51.48,70.352],[-2.197,1.417],[-2.304,2.508]],"v":[[-38.728,71.71],[70.476,-31.156],[91.481,-81.05],[91.487,-86.528],[91.442,-84.514],[70.437,-34.62],[-38.767,68.246],[-47.802,58.136]]},"ix":2}},{"ty":"fl","bm":0,"hd":false,"mn":"ADBE Vector Graphic - Fill","nm":"Fill 1","c":{"a":0,"k":[0.8157,0.8078,0.949],"ix":4},"r":1,"o":{"a":0,"k":100,"ix":5}},{"ty":"tr","a":{"a":0,"k":[0,0],"ix":1},"s":{"a":0,"k":[100,100],"ix":3},"sk":{"a":0,"k":0,"ix":4},"p":{"a":0,"k":[0,0],"ix":2},"r":{"a":0,"k":0,"ix":6},"sa":{"a":0,"k":0,"ix":5},"o":{"a":0,"k":100,"ix":7}}]},{"ty":"gr","bm":0,"hd":false,"mn":"ADBE Vector Group","nm":"Group 5","ix":5,"cix":2,"np":2,"it":[{"ty":"sh","bm":0,"hd":false,"mn":"ADBE Vector Shape - Group","nm":"Path 1","ix":1,"d":1,"ks":{"a":0,"k":{"c":true,"i":[[17.905,-9.861],[-3.016,1.94],[-51.48,70.352],[-0.701,21.006],[2.462,-6.283]],"o":[[-3.016,1.94],[0,0],[6.539,-8.943],[0.704,-21.01],[-23.908,61.032]],"v":[[-47.579,57.945],[-38.728,71.71],[70.476,-31.156],[91.481,-81.05],[82.828,-96.559]]},"ix":2}},{"ty":"fl","bm":0,"hd":false,"mn":"ADBE Vector Graphic - Fill","nm":"Fill 1","c":{"a":0,"k":[0.9529,0.9451,0.9882],"ix":4},"r":1,"o":{"a":0,"k":100,"ix":5}},{"ty":"tr","a":{"a":0,"k":[0,0],"ix":1},"s":{"a":0,"k":[100,100],"ix":3},"sk":{"a":0,"k":0,"ix":4},"p":{"a":0,"k":[0,0],"ix":2},"r":{"a":0,"k":0,"ix":6},"sa":{"a":0,"k":0,"ix":5},"o":{"a":0,"k":100,"ix":7}}]},{"ty":"gr","bm":0,"hd":false,"mn":"ADBE Vector Group","nm":"Group 6","ix":6,"cix":2,"np":2,"it":[{"ty":"sh","bm":0,"hd":false,"mn":"ADBE Vector Shape - Group","nm":"Path 1","ix":1,"d":1,"ks":{"a":0,"k":{"c":true,"i":[[-3.732,2.596],[3.732,-2.596]],"o":[[3.732,-2.596],[-3.732,2.596]],"v":[[-38.172,73.115],[-48.493,57.083]]},"ix":2}},{"ty":"fl","bm":0,"hd":false,"mn":"ADBE Vector Graphic - Fill","nm":"Fill 1","c":{"a":0,"k":[0.6471,0.6471,0.6471],"ix":4},"r":1,"o":{"a":0,"k":100,"ix":5}},{"ty":"tr","a":{"a":0,"k":[0,0],"ix":1},"s":{"a":0,"k":[100,100],"ix":3},"sk":{"a":0,"k":0,"ix":4},"p":{"a":0,"k":[0,0],"ix":2},"r":{"a":0,"k":0,"ix":6},"sa":{"a":0,"k":0,"ix":5},"o":{"a":0,"k":100,"ix":7}}]},{"ty":"gr","bm":0,"hd":false,"mn":"ADBE Vector Group","nm":"Group 7","ix":7,"cix":2,"np":2,"it":[{"ty":"sh","bm":0,"hd":false,"mn":"ADBE Vector Shape - Group","nm":"Path 1","ix":1,"d":1,"ks":{"a":0,"k":{"c":true,"i":[[-3.733,2.6],[0,0],[0,0],[3.334,2.379],[0,0],[0,0],[0,0],[0.048,-0.033]],"o":[[0,0],[0,0],[-0.502,-3.865],[0,0],[0,0],[0,0],[-0.052,0.03],[-3.73,2.596]],"v":[[-41.381,75.234],[-38.324,73.208],[-40.632,72.534],[-48.517,59.846],[-48.493,57.085],[-51.54,59.105],[-51.55,59.111],[-51.703,59.205]]},"ix":2}},{"ty":"fl","bm":0,"hd":false,"mn":"ADBE Vector Graphic - Fill","nm":"Fill 1","c":{"a":0,"k":[0.7451,0.7451,0.7451],"ix":4},"r":1,"o":{"a":0,"k":100,"ix":5}},{"ty":"tr","a":{"a":0,"k":[0,0],"ix":1},"s":{"a":0,"k":[100,100],"ix":3},"sk":{"a":0,"k":0,"ix":4},"p":{"a":0,"k":[0,0],"ix":2},"r":{"a":0,"k":0,"ix":6},"sa":{"a":0,"k":0,"ix":5},"o":{"a":0,"k":100,"ix":7}}]},{"ty":"gr","bm":0,"hd":false,"mn":"ADBE Vector Group","nm":"Group 8","ix":8,"cix":2,"np":2,"it":[{"ty":"sh","bm":0,"hd":false,"mn":"ADBE Vector Shape - Group","nm":"Path 1","ix":1,"d":1,"ks":{"a":0,"k":{"c":true,"i":[[-4.255,-6.792],[-3.928,0.202],[3.117,4.793],[-3.95,2.477],[-3.549,-2.773],[2.919,-1.825]],"o":[[3.404,5.442],[-3.682,-0.35],[-4.277,-6.58],[2.649,-1.652],[-3.769,-3.405],[-4.042,2.527]],"v":[[-53.216,71.97],[-40.89,80.507],[-52.079,72.303],[-52.665,55.9],[-42.602,57.953],[-53.601,55.084]]},"ix":2}},{"ty":"fl","bm":0,"hd":false,"mn":"ADBE Vector Graphic - Fill","nm":"Fill 1","c":{"a":0,"k":[0.7451,0.7451,0.7451],"ix":4},"r":1,"o":{"a":0,"k":100,"ix":5}},{"ty":"tr","a":{"a":0,"k":[0,0],"ix":1},"s":{"a":0,"k":[100,100],"ix":3},"sk":{"a":0,"k":0,"ix":4},"p":{"a":0,"k":[0,0],"ix":2},"r":{"a":0,"k":0,"ix":6},"sa":{"a":0,"k":0,"ix":5},"o":{"a":0,"k":100,"ix":7}}]},{"ty":"gr","bm":0,"hd":false,"mn":"ADBE Vector Group","nm":"Group 9","ix":9,"cix":2,"np":2,"it":[{"ty":"sh","bm":0,"hd":false,"mn":"ADBE Vector Shape - Group","nm":"Path 1","ix":1,"d":1,"ks":{"a":0,"k":{"c":true,"i":[[2.09,-1.309],[-3.547,-5.924],[-2.085,1.305],[3.11,4.76]],"o":[[-2.085,1.305],[3.418,5.708],[2.09,-1.309],[-3.11,-4.76]],"v":[[-52.022,58.517],[-50.168,69.504],[-40.759,75.755],[-42.605,64.769]]},"ix":2}},{"ty":"fl","bm":0,"hd":false,"mn":"ADBE Vector Graphic - Fill","nm":"Fill 1","c":{"a":0,"k":[0.8,0.8,0.8],"ix":4},"r":1,"o":{"a":0,"k":100,"ix":5}},{"ty":"tr","a":{"a":0,"k":[0,0],"ix":1},"s":{"a":0,"k":[100,100],"ix":3},"sk":{"a":0,"k":0,"ix":4},"p":{"a":0,"k":[0,0],"ix":2},"r":{"a":0,"k":0,"ix":6},"sa":{"a":0,"k":0,"ix":5},"o":{"a":0,"k":100,"ix":7}}]},{"ty":"gr","bm":0,"hd":false,"mn":"ADBE Vector Group","nm":"Group 10","ix":10,"cix":2,"np":2,"it":[{"ty":"sh","bm":0,"hd":false,"mn":"ADBE Vector Shape - Group","nm":"Path 1","ix":1,"d":1,"ks":{"a":0,"k":{"c":true,"i":[[4.048,-2.534],[-4.253,-6.795],[-4.038,2.528],[4.253,6.795]],"o":[[-4.038,2.528],[4.253,6.795],[4.048,-2.534],[-4.253,-6.795]],"v":[[-53.602,55.085],[-53.218,71.972],[-38.201,79.69],[-38.571,62.803]]},"ix":2}},{"ty":"fl","bm":0,"hd":false,"mn":"ADBE Vector Graphic - Fill","nm":"Fill 1","c":{"a":0,"k":[0.9098,0.9098,0.9098],"ix":4},"r":1,"o":{"a":0,"k":100,"ix":5}},{"ty":"tr","a":{"a":0,"k":[0,0],"ix":1},"s":{"a":0,"k":[100,100],"ix":3},"sk":{"a":0,"k":0,"ix":4},"p":{"a":0,"k":[0,0],"ix":2},"r":{"a":0,"k":0,"ix":6},"sa":{"a":0,"k":0,"ix":5},"o":{"a":0,"k":100,"ix":7}}]},{"ty":"gr","bm":0,"hd":false,"mn":"ADBE Vector Group","nm":"Group 11","ix":11,"cix":2,"np":2,"it":[{"ty":"sh","bm":0,"hd":false,"mn":"ADBE Vector Shape - Group","nm":"Path 1","ix":1,"d":1,"ks":{"a":0,"k":{"c":true,"i":[[0.295,-0.656],[0.003,-0.005],[-3.261,-5.205],[-3.947,0.094],[-1.638,2.699],[0.453,-0.137],[3.132,4.997],[3.856,0.075],[-0.135,0.443],[1.36,-1.525]],"o":[[-0.008,0.002],[-1.59,3.496],[3.433,5.487],[2.597,-0.062],[-0.481,0.06],[1.351,-3.517],[-3.268,-5.223],[0.194,-0.385],[-1.804,0.346],[-0.452,0.507]],"v":[[-57.645,58.958],[-57.657,58.977],[-55.131,73.333],[-42.711,81.866],[-36.387,77.802],[-37.787,78.095],[-40.484,64.166],[-52.331,55.62],[-51.835,54.382],[-56.49,57.24]]},"ix":2}},{"ty":"fl","bm":0,"hd":false,"mn":"ADBE Vector Graphic - Fill","nm":"Fill 1","c":{"a":0,"k":[0.8,0.8,0.8],"ix":4},"r":1,"o":{"a":0,"k":100,"ix":5}},{"ty":"tr","a":{"a":0,"k":[0,0],"ix":1},"s":{"a":0,"k":[100,100],"ix":3},"sk":{"a":0,"k":0,"ix":4},"p":{"a":0,"k":[0,0],"ix":2},"r":{"a":0,"k":0,"ix":6},"sa":{"a":0,"k":0,"ix":5},"o":{"a":0,"k":100,"ix":7}}]},{"ty":"gr","bm":0,"hd":false,"mn":"ADBE Vector Group","nm":"Group 12","ix":12,"cix":2,"np":2,"it":[{"ty":"sh","bm":0,"hd":false,"mn":"ADBE Vector Shape - Group","nm":"Path 1","ix":1,"d":1,"ks":{"a":0,"k":{"c":true,"i":[[-0.203,-1.399],[0,0],[-0.526,0.731],[-0.305,0.208],[0,0],[0,0]],"o":[[0,0],[-0.14,-1.02],[0.194,-0.275],[0,0],[0,0],[-1.136,0.771]],"v":[[-59.961,70.969],[-57.562,69.432],[-57.038,66.74],[-56.29,66.006],[-57.154,66.56],[-58.696,67.545]]},"ix":2}},{"ty":"fl","bm":0,"hd":false,"mn":"ADBE Vector Graphic - Fill","nm":"Fill 1","c":{"a":0,"k":[0.7255,0.7255,0.7255],"ix":4},"r":1,"o":{"a":0,"k":100,"ix":5}},{"ty":"tr","a":{"a":0,"k":[0,0],"ix":1},"s":{"a":0,"k":[100,100],"ix":3},"sk":{"a":0,"k":0,"ix":4},"p":{"a":0,"k":[0,0],"ix":2},"r":{"a":0,"k":0,"ix":6},"sa":{"a":0,"k":0,"ix":5},"o":{"a":0,"k":100,"ix":7}}]},{"ty":"gr","bm":0,"hd":false,"mn":"ADBE Vector Group","nm":"Group 13","ix":13,"cix":2,"np":2,"it":[{"ty":"sh","bm":0,"hd":false,"mn":"ADBE Vector Shape - Group","nm":"Path 1","ix":1,"d":1,"ks":{"a":0,"k":{"c":true,"i":[[-0.203,-1.399],[-2.871,1.713],[0,0],[0,0],[0.343,-0.028],[0.505,3.614],[-0.526,0.731],[-0.305,0.208],[0,0],[0,0]],"o":[[0.572,4.035],[0,0],[0,0],[-0.307,0.181],[-2.907,0.308],[-0.14,-1.02],[0.194,-0.275],[0,0],[0,0],[-1.136,0.771]],"v":[[-59.961,70.969],[-51.513,78.519],[-49.976,77.532],[-49.146,77],[-50.118,77.315],[-57.562,69.432],[-57.038,66.74],[-56.29,66.006],[-57.154,66.56],[-58.696,67.545]]},"ix":2}},{"ty":"fl","bm":0,"hd":false,"mn":"ADBE Vector Graphic - Fill","nm":"Fill 1","c":{"a":0,"k":[0.8392,0.8392,0.8392],"ix":4},"r":1,"o":{"a":0,"k":100,"ix":5}},{"ty":"tr","a":{"a":0,"k":[0,0],"ix":1},"s":{"a":0,"k":[100,100],"ix":3},"sk":{"a":0,"k":0,"ix":4},"p":{"a":0,"k":[0,0],"ix":2},"r":{"a":0,"k":0,"ix":6},"sa":{"a":0,"k":0,"ix":5},"o":{"a":0,"k":100,"ix":7}}]},{"ty":"gr","bm":0,"hd":false,"mn":"ADBE Vector Group","nm":"Group 14","ix":14,"cix":2,"np":2,"it":[{"ty":"sh","bm":0,"hd":false,"mn":"ADBE Vector Shape - Group","nm":"Path 1","ix":1,"d":1,"ks":{"a":0,"k":{"c":true,"i":[[-0.203,-1.399],[-2.864,1.712],[0,0],[0.554,4.043],[-1.132,0.774],[0,0]],"o":[[0.575,4.03],[0,0],[-2.87,1.721],[-0.196,-1.4],[0,0],[-1.136,0.771]],"v":[[-66.288,75.03],[-57.846,82.577],[-55.478,81.058],[-63.887,73.488],[-62.619,70.059],[-65.024,71.606]]},"ix":2}},{"ty":"fl","bm":0,"hd":false,"mn":"ADBE Vector Graphic - Fill","nm":"Fill 1","c":{"a":0,"k":[0.8392,0.8392,0.8392],"ix":4},"r":1,"o":{"a":0,"k":100,"ix":5}},{"ty":"tr","a":{"a":0,"k":[0,0],"ix":1},"s":{"a":0,"k":[100,100],"ix":3},"sk":{"a":0,"k":0,"ix":4},"p":{"a":0,"k":[0,0],"ix":2},"r":{"a":0,"k":0,"ix":6},"sa":{"a":0,"k":0,"ix":5},"o":{"a":0,"k":100,"ix":7}}]},{"ty":"gr","bm":0,"hd":false,"mn":"ADBE Vector Group","nm":"Group 15","ix":15,"cix":2,"np":2,"it":[{"ty":"sh","bm":0,"hd":false,"mn":"ADBE Vector Shape - Group","nm":"Path 1","ix":1,"d":1,"ks":{"a":0,"k":{"c":true,"i":[[-0.199,-1.396],[-2.868,1.709],[0,0],[0.559,4.046],[0,0],[-1.132,0.774],[0,0]],"o":[[0.58,4.033],[0,0],[-2.871,1.713],[0,0],[-0.199,-1.396],[0,0],[-1.139,0.776]],"v":[[-72.62,79.088],[-64.173,86.638],[-61.806,85.118],[-70.219,77.546],[-70.216,77.541],[-68.947,74.12],[-71.353,75.659]]},"ix":2}},{"ty":"fl","bm":0,"hd":false,"mn":"ADBE Vector Graphic - Fill","nm":"Fill 1","c":{"a":0,"k":[0.8392,0.8392,0.8392],"ix":4},"r":1,"o":{"a":0,"k":100,"ix":5}},{"ty":"tr","a":{"a":0,"k":[0,0],"ix":1},"s":{"a":0,"k":[100,100],"ix":3},"sk":{"a":0,"k":0,"ix":4},"p":{"a":0,"k":[0,0],"ix":2},"r":{"a":0,"k":0,"ix":6},"sa":{"a":0,"k":0,"ix":5},"o":{"a":0,"k":100,"ix":7}}]},{"ty":"gr","bm":0,"hd":false,"mn":"ADBE Vector Group","nm":"Group 16","ix":16,"cix":2,"np":2,"it":[{"ty":"sh","bm":0,"hd":false,"mn":"ADBE Vector Shape - Group","nm":"Path 1","ix":1,"d":1,"ks":{"a":0,"k":{"c":true,"i":[[-0.203,-1.399],[-2.871,1.713],[0,0],[0.554,4.043],[-1.132,0.774],[0,0]],"o":[[0.568,4.032],[0,0],[-2.871,1.713],[-0.199,-1.396],[0,0],[-1.136,0.771]],"v":[[-78.945,83.144],[-70.498,90.694],[-68.134,89.179],[-76.543,81.602],[-75.274,78.18],[-77.68,79.719]]},"ix":2}},{"ty":"fl","bm":0,"hd":false,"mn":"ADBE Vector Graphic - Fill","nm":"Fill 1","c":{"a":0,"k":[0.8392,0.8392,0.8392],"ix":4},"r":1,"o":{"a":0,"k":100,"ix":5}},{"ty":"tr","a":{"a":0,"k":[0,0],"ix":1},"s":{"a":0,"k":[100,100],"ix":3},"sk":{"a":0,"k":0,"ix":4},"p":{"a":0,"k":[0,0],"ix":2},"r":{"a":0,"k":0,"ix":6},"sa":{"a":0,"k":0,"ix":5},"o":{"a":0,"k":100,"ix":7}}]},{"ty":"gr","bm":0,"hd":false,"mn":"ADBE Vector Group","nm":"Group 17","ix":17,"cix":2,"np":2,"it":[{"ty":"sh","bm":0,"hd":false,"mn":"ADBE Vector Shape - Group","nm":"Path 1","ix":1,"d":1,"ks":{"a":0,"k":{"c":true,"i":[[-2.094,-2.894],[-1.304,1.401],[-0.271,0.185],[0,0],[-0.002,0.141],[-0.621,0.422],[0,0],[0,0],[0,0],[0,0],[-0.305,0.208],[0,0],[0,0],[0,0],[0,0],[0,0]],"o":[[-0.689,-2.179],[0.207,-0.227],[0,0],[-0.019,-0.149],[-0.007,-0.907],[0,0],[0,0],[0,0],[0,0],[0.194,-0.275],[0,0],[0,0],[0,0],[0,0],[0,0],[-2.43,1.653]],"v":[[-84.224,91.916],[-83.541,86.247],[-82.823,85.629],[-82.474,85.404],[-82.501,84.972],[-81.589,83.002],[-57.809,67.745],[-56.957,69.045],[-55.951,68.402],[-57.038,66.74],[-56.29,66.006],[-57.154,66.56],[-57.456,66.102],[-82.26,82.009],[-82.263,82.014],[-84.863,83.679]]},"ix":2}},{"ty":"fl","bm":0,"hd":false,"mn":"ADBE Vector Graphic - Fill","nm":"Fill 1","c":{"a":0,"k":[0.7255,0.7255,0.7255],"ix":4},"r":1,"o":{"a":0,"k":100,"ix":5}},{"ty":"tr","a":{"a":0,"k":[0,0],"ix":1},"s":{"a":0,"k":[100,100],"ix":3},"sk":{"a":0,"k":0,"ix":4},"p":{"a":0,"k":[0,0],"ix":2},"r":{"a":0,"k":0,"ix":6},"sa":{"a":0,"k":0,"ix":5},"o":{"a":0,"k":100,"ix":7}}]},{"ty":"gr","bm":0,"hd":false,"mn":"ADBE Vector Group","nm":"Group 18","ix":18,"cix":2,"np":2,"it":[{"ty":"sh","bm":0,"hd":false,"mn":"ADBE Vector Shape - Group","nm":"Path 1","ix":1,"d":1,"ks":{"a":0,"k":{"c":true,"i":[[-2.094,-2.894],[-2.049,1.222],[0,0],[0.936,4.281],[-1.365,0.932],[0,0]],"o":[[2.018,2.793],[0,0],[-2.979,1.779],[-0.38,-1.722],[0,0],[-2.43,1.653]],"v":[[-84.224,91.916],[-77.102,95.54],[-74.544,93.899],[-83.541,86.247],[-82.263,82.014],[-84.863,83.679]]},"ix":2}},{"ty":"fl","bm":0,"hd":false,"mn":"ADBE Vector Graphic - Fill","nm":"Fill 1","c":{"a":0,"k":[0.8392,0.8392,0.8392],"ix":4},"r":1,"o":{"a":0,"k":100,"ix":5}},{"ty":"tr","a":{"a":0,"k":[0,0],"ix":1},"s":{"a":0,"k":[100,100],"ix":3},"sk":{"a":0,"k":0,"ix":4},"p":{"a":0,"k":[0,0],"ix":2},"r":{"a":0,"k":0,"ix":6},"sa":{"a":0,"k":0,"ix":5},"o":{"a":0,"k":100,"ix":7}}]},{"ty":"gr","bm":0,"hd":false,"mn":"ADBE Vector Group","nm":"Group 19","ix":19,"cix":2,"np":2,"it":[{"ty":"sh","bm":0,"hd":false,"mn":"ADBE Vector Shape - Group","nm":"Path 1","ix":1,"d":1,"ks":{"a":0,"k":{"c":true,"i":[[-2.416,-1.588],[-0.87,0.52],[0,0],[0,0],[0,0],[-0.008,-0.903]],"o":[[0.66,0.434],[0,0],[0,0],[0,0],[-0.621,0.424],[0.021,2.322]],"v":[[-77.925,92.311],[-75.156,92.875],[-51.352,77.609],[-57.807,67.744],[-81.59,82.998],[-82.5,84.971]]},"ix":2}},{"ty":"fl","bm":0,"hd":false,"mn":"ADBE Vector Graphic - Fill","nm":"Fill 1","c":{"a":0,"k":[0.7255,0.7255,0.7255],"ix":4},"r":1,"o":{"a":0,"k":100,"ix":5}},{"ty":"tr","a":{"a":0,"k":[0,0],"ix":1},"s":{"a":0,"k":[100,100],"ix":3},"sk":{"a":0,"k":0,"ix":4},"p":{"a":0,"k":[0,0],"ix":2},"r":{"a":0,"k":0,"ix":6},"sa":{"a":0,"k":0,"ix":5},"o":{"a":0,"k":100,"ix":7}}]},{"ty":"gr","bm":0,"hd":false,"mn":"ADBE Vector Group","nm":"Group 20","ix":20,"cix":2,"np":2,"it":[{"ty":"sh","bm":0,"hd":false,"mn":"ADBE Vector Shape - Group","nm":"Path 1","ix":1,"d":1,"ks":{"a":0,"k":{"c":true,"i":[[-0.38,-1.722],[-2.979,1.779],[0,0],[0,0],[0,0],[0,0],[0,0],[0,0],[0,0],[0,0],[0,0]],"o":[[0.936,4.281],[0,0],[0,0],[0,0],[0,0],[0,0],[0,0],[0,0],[0,0],[0,0],[-1.365,0.932]],"v":[[-83.541,86.247],[-74.544,93.899],[-49.695,77.963],[-49.976,77.532],[-50.118,77.315],[-55.951,68.402],[-57.038,66.74],[-57.154,66.56],[-57.456,66.102],[-82.26,82.009],[-82.263,82.014]]},"ix":2}},{"ty":"fl","bm":0,"hd":false,"mn":"ADBE Vector Graphic - Fill","nm":"Fill 1","c":{"a":0,"k":[0.8392,0.8392,0.8392],"ix":4},"r":1,"o":{"a":0,"k":100,"ix":5}},{"ty":"tr","a":{"a":0,"k":[0,0],"ix":1},"s":{"a":0,"k":[100,100],"ix":3},"sk":{"a":0,"k":0,"ix":4},"p":{"a":0,"k":[0,0],"ix":2},"r":{"a":0,"k":0,"ix":6},"sa":{"a":0,"k":0,"ix":5},"o":{"a":0,"k":100,"ix":7}}]},{"ty":"gr","bm":0,"hd":false,"mn":"ADBE Vector Group","nm":"Group 21","ix":21,"cix":2,"np":2,"it":[{"ty":"sh","bm":0,"hd":false,"mn":"ADBE Vector Shape - Group","nm":"Path 1","ix":1,"d":1,"ks":{"a":0,"k":{"c":true,"i":[[-5.362,3.203],[0,0],[-4.066,2.771],[0,0],[0,0],[0,0]],"o":[[0,0],[-4.288,-3.603],[0,0],[0,0],[0,0],[-6.124,4.175]],"v":[[-79.728,99.535],[-79.237,99.222],[-82.823,85.629],[-51.856,65.774],[-54.5,61.733],[-89.697,84.303]]},"ix":2}},{"ty":"fl","bm":0,"hd":false,"mn":"ADBE Vector Graphic - Fill","nm":"Fill 1","c":{"a":0,"k":[0.6745,0.6745,0.6745],"ix":4},"r":1,"o":{"a":0,"k":100,"ix":5}},{"ty":"tr","a":{"a":0,"k":[0,0],"ix":1},"s":{"a":0,"k":[100,100],"ix":3},"sk":{"a":0,"k":0,"ix":4},"p":{"a":0,"k":[0,0],"ix":2},"r":{"a":0,"k":0,"ix":6},"sa":{"a":0,"k":0,"ix":5},"o":{"a":0,"k":100,"ix":7}}]},{"ty":"gr","bm":0,"hd":false,"mn":"ADBE Vector Group","nm":"Group 22","ix":22,"cix":2,"np":2,"it":[{"ty":"sh","bm":0,"hd":false,"mn":"ADBE Vector Shape - Group","nm":"Path 1","ix":1,"d":1,"ks":{"a":0,"k":{"c":true,"i":[[-5.362,3.203],[0,0],[0,0],[0,0]],"o":[[0,0],[0,0],[0,0],[-6.124,4.175]],"v":[[-79.728,99.535],[-44.53,76.965],[-54.5,61.733],[-89.697,84.303]]},"ix":2}},{"ty":"fl","bm":0,"hd":false,"mn":"ADBE Vector Graphic - Fill","nm":"Fill 1","c":{"a":0,"k":[0.7255,0.7255,0.7255],"ix":4},"r":1,"o":{"a":0,"k":100,"ix":5}},{"ty":"tr","a":{"a":0,"k":[0,0],"ix":1},"s":{"a":0,"k":[100,100],"ix":3},"sk":{"a":0,"k":0,"ix":4},"p":{"a":0,"k":[0,0],"ix":2},"r":{"a":0,"k":0,"ix":6},"sa":{"a":0,"k":0,"ix":5},"o":{"a":0,"k":100,"ix":7}}]}],"ind":2,"parent":6},{"ty":4,"nm":"Layer 5","sr":1,"st":5,"op":25,"ip":5,"hd":false,"ddd":0,"bm":0,"tt":1,"hasMask":false,"ao":0,"ks":{"a":{"a":0,"k":[0,0,0],"ix":1},"s":{"a":0,"k":[100,100,100],"ix":6},"sk":{"a":0,"k":0},"p":{"a":1,"k":[{"o":{"x":0.167,"y":0.167},"i":{"x":0.833,"y":0.833},"s":[119.085,-73.852,0],"t":5,"ti":[22.745,-17.789,0],"to":[-22.745,17.789,0]},{"s":[-17.386,32.884,0],"t":24}],"ix":2},"r":{"a":0,"k":-1,"ix":10},"sa":{"a":0,"k":0},"o":{"a":1,"k":[{"o":{"x":0.167,"y":0.167},"i":{"x":0.833,"y":0.833},"s":[48],"t":23},{"s":[0],"t":24}],"ix":11}},"ef":[],"shapes":[{"ty":"gr","bm":0,"hd":false,"mn":"ADBE Vector Group","nm":"Group 1","ix":1,"cix":2,"np":2,"it":[{"ty":"sh","bm":0,"hd":false,"mn":"ADBE Vector Shape - Group","nm":"Path 1","ix":1,"d":1,"ks":{"a":0,"k":{"c":true,"i":[[0,0],[0,0],[0,0],[0,0]],"o":[[0,0],[0,0],[0,0],[0,0]],"v":[[11.08,118.796],[7.044,118.796],[7.044,-136.857],[11.08,-136.857]]},"ix":2}},{"ty":"fl","bm":0,"hd":false,"mn":"ADBE Vector Graphic - Fill","nm":"Fill 1","c":{"a":0,"k":[1,1,1],"ix":4},"r":1,"o":{"a":0,"k":100,"ix":5}},{"ty":"tr","a":{"a":0,"k":[0,0],"ix":1},"s":{"a":0,"k":[100,100],"ix":3},"sk":{"a":0,"k":0,"ix":4},"p":{"a":0,"k":[0,0],"ix":2},"r":{"a":0,"k":0,"ix":6},"sa":{"a":0,"k":0,"ix":5},"o":{"a":0,"k":100,"ix":7}}]},{"ty":"gr","bm":0,"hd":false,"mn":"ADBE Vector Group","nm":"Group 2","ix":2,"cix":2,"np":2,"it":[{"ty":"sh","bm":0,"hd":false,"mn":"ADBE Vector Shape - Group","nm":"Path 1","ix":1,"d":1,"ks":{"a":0,"k":{"c":true,"i":[[0,0],[0,0],[0,0],[0,0]],"o":[[0,0],[0,0],[0,0],[0,0]],"v":[[-0.221,118.796],[-16.031,118.796],[-16.031,-136.857],[-0.221,-136.857]]},"ix":2}},{"ty":"fl","bm":0,"hd":false,"mn":"ADBE Vector Graphic - Fill","nm":"Fill 1","c":{"a":0,"k":[1,1,1],"ix":4},"r":1,"o":{"a":0,"k":100,"ix":5}},{"ty":"tr","a":{"a":0,"k":[0,0],"ix":1},"s":{"a":0,"k":[100,100],"ix":3},"sk":{"a":0,"k":0,"ix":4},"p":{"a":0,"k":[0,0],"ix":2},"r":{"a":0,"k":0,"ix":6},"sa":{"a":0,"k":0,"ix":5},"o":{"a":0,"k":100,"ix":7}}]}],"ind":3,"parent":6},{"ty":4,"nm":"Layer 4","sr":1,"st":0,"op":20,"ip":0,"hd":false,"ddd":0,"bm":0,"hasMask":false,"td":1,"ao":0,"ks":{"a":{"a":0,"k":[51.775,74.142,0],"ix":1},"s":{"a":0,"k":[100,100,100],"ix":6},"sk":{"a":0,"k":0},"p":{"a":1,"k":[{"o":{"x":0.333,"y":0},"i":{"x":0.407,"y":1},"s":[51.775,74.142,0],"t":0,"ti":[0,0,0],"to":[-2.357,-2.357,0]},{"o":{"x":0.606,"y":0},"i":{"x":0.667,"y":1},"s":[37.633,60,0],"t":10,"ti":[-2.357,-2.357,0],"to":[0,0,0]},{"o":{"x":0.167,"y":0.167},"i":{"x":0.833,"y":0.833},"s":[51.775,74.142,0],"t":20,"ti":[0,0,0],"to":[0,0,0]},{"o":{"x":0.167,"y":0.167},"i":{"x":0.833,"y":0.833},"s":[51.775,74.142,0],"t":45,"ti":[5.303,-1.768,0],"to":[-5.303,1.768,0]},{"o":{"x":0.167,"y":0.167},"i":{"x":0.833,"y":0.833},"s":[19.955,84.749,0],"t":50,"ti":[0,0,0],"to":[0,0,0]},{"o":{"x":0.167,"y":0.167},"i":{"x":0.667,"y":1},"s":[19.955,84.749,0],"t":55,"ti":[-5.303,1.768,0],"to":[5.303,-1.768,0]},{"s":[51.775,74.142,0],"t":66}],"ix":2},"r":{"a":1,"k":[{"o":{"x":0.167,"y":0.167},"i":{"x":0.833,"y":0.833},"s":[0],"t":30},{"o":{"x":0.167,"y":0.167},"i":{"x":0.833,"y":0.833},"s":[20],"t":35},{"o":{"x":0.167,"y":0.167},"i":{"x":0.833,"y":0.833},"s":[-34],"t":40},{"o":{"x":0.167,"y":0.167},"i":{"x":0.833,"y":0.833},"s":[-36],"t":45},{"o":{"x":0.167,"y":0.167},"i":{"x":0.833,"y":0.833},"s":[-41],"t":50},{"o":{"x":0.167,"y":0.167},"i":{"x":0.833,"y":0.833},"s":[-5],"t":55},{"o":{"x":0.167,"y":0.167},"i":{"x":0.667,"y":1},"s":[18],"t":60},{"o":{"x":0.333,"y":0},"i":{"x":0.667,"y":1},"s":[0],"t":66},{"o":{"x":0.333,"y":0},"i":{"x":0.667,"y":1},"s":[-20],"t":73},{"s":[0],"t":80}],"ix":10},"sa":{"a":0,"k":0},"o":{"a":0,"k":100,"ix":11}},"ef":[],"shapes":[{"ty":"gr","bm":0,"hd":false,"mn":"ADBE Vector Group","nm":"Group 1","ix":1,"cix":2,"np":2,"it":[{"ty":"sh","bm":0,"hd":false,"mn":"ADBE Vector Shape - Group","nm":"Path 1","ix":1,"d":1,"ks":{"a":0,"k":{"c":true,"i":[[0.203,-1.399],[0,0],[1.132,0.774],[0,0]],"o":[[0,0],[0.199,-1.396],[0,0],[1.136,0.771]],"v":[[78.945,83.144],[76.543,81.602],[75.274,78.18],[77.68,79.719]]},"ix":2}},{"ty":"fl","bm":0,"hd":false,"mn":"ADBE Vector Graphic - Fill","nm":"Fill 1","c":{"a":0,"k":[0.7255,0.7255,0.7255],"ix":4},"r":1,"o":{"a":0,"k":100,"ix":5}},{"ty":"tr","a":{"a":0,"k":[0,0],"ix":1},"s":{"a":0,"k":[100,100],"ix":3},"sk":{"a":0,"k":0,"ix":4},"p":{"a":0,"k":[0,0],"ix":2},"r":{"a":0,"k":0,"ix":6},"sa":{"a":0,"k":0,"ix":5},"o":{"a":0,"k":100,"ix":7}}]},{"ty":"gr","bm":0,"hd":false,"mn":"ADBE Vector Group","nm":"Group 2","ix":2,"cix":2,"np":2,"it":[{"ty":"sh","bm":0,"hd":false,"mn":"ADBE Vector Shape - Group","nm":"Path 1","ix":1,"d":1,"ks":{"a":0,"k":{"c":true,"i":[[0,0],[0.199,-1.396],[0,0],[0,0],[1.132,0.774]],"o":[[1.139,0.776],[0,0],[0,0],[0.199,-1.396],[0,0]],"v":[[71.353,75.659],[72.62,79.088],[70.219,77.546],[70.216,77.541],[68.947,74.12]]},"ix":2}},{"ty":"fl","bm":0,"hd":false,"mn":"ADBE Vector Graphic - Fill","nm":"Fill 1","c":{"a":0,"k":[0.7255,0.7255,0.7255],"ix":4},"r":1,"o":{"a":0,"k":100,"ix":5}},{"ty":"tr","a":{"a":0,"k":[0,0],"ix":1},"s":{"a":0,"k":[100,100],"ix":3},"sk":{"a":0,"k":0,"ix":4},"p":{"a":0,"k":[0,0],"ix":2},"r":{"a":0,"k":0,"ix":6},"sa":{"a":0,"k":0,"ix":5},"o":{"a":0,"k":100,"ix":7}}]},{"ty":"gr","bm":0,"hd":false,"mn":"ADBE Vector Group","nm":"Group 3","ix":3,"cix":2,"np":2,"it":[{"ty":"sh","bm":0,"hd":false,"mn":"ADBE Vector Shape - Group","nm":"Path 1","ix":1,"d":1,"ks":{"a":0,"k":{"c":true,"i":[[0,0],[0.203,-1.399],[0,0],[1.132,0.774]],"o":[[1.136,0.771],[0,0],[0.196,-1.4],[0,0]],"v":[[65.024,71.606],[66.288,75.03],[63.887,73.488],[62.619,70.059]]},"ix":2}},{"ty":"fl","bm":0,"hd":false,"mn":"ADBE Vector Graphic - Fill","nm":"Fill 1","c":{"a":0,"k":[0.7255,0.7255,0.7255],"ix":4},"r":1,"o":{"a":0,"k":100,"ix":5}},{"ty":"tr","a":{"a":0,"k":[0,0],"ix":1},"s":{"a":0,"k":[100,100],"ix":3},"sk":{"a":0,"k":0,"ix":4},"p":{"a":0,"k":[0,0],"ix":2},"r":{"a":0,"k":0,"ix":6},"sa":{"a":0,"k":0,"ix":5},"o":{"a":0,"k":100,"ix":7}}]},{"ty":"gr","bm":0,"hd":false,"mn":"ADBE Vector Group","nm":"Group 4","ix":4,"cix":2,"np":2,"it":[{"ty":"sh","bm":0,"hd":false,"mn":"ADBE Vector Shape - Group","nm":"Path 1","ix":1,"d":1,"ks":{"a":0,"k":{"c":true,"i":[[2.937,1.875],[21.437,17.5],[2.438,2.126],[4.313,4.063],[17.875,24.5],[0.687,21],[0,1.625],[0,-0.688],[-6.5,-8.938],[-17.188,-15.75],[-6.125,-4.875],[0,0],[-1.563,4.562]],"o":[[0,0],[-2.312,-1.875],[-4,-3.438],[-16.75,-15.5],[-6.562,-8.938],[-0.063,-2],[0.063,0.625],[0.687,20.999],[18.563,25.312],[7.063,6.499],[20.313,16.312],[2.187,1.437],[2.312,2.5]],"v":[[38.732,71.718],[2.419,45.842],[-4.706,39.905],[-17.206,28.717],[-70.456,-31.157],[-91.456,-81.032],[-91.518,-86.532],[-91.456,-84.532],[-70.456,-34.594],[-15.331,26.905],[4.544,44.03],[38.794,68.218],[47.794,58.155]]},"ix":2}},{"ty":"fl","bm":0,"hd":false,"mn":"ADBE Vector Graphic - Fill","nm":"Fill 1","c":{"a":0,"k":[0.8157,0.8078,0.949],"ix":4},"r":1,"o":{"a":0,"k":100,"ix":5}},{"ty":"tr","a":{"a":0,"k":[0,0],"ix":1},"s":{"a":0,"k":[100,100],"ix":3},"sk":{"a":0,"k":0,"ix":4},"p":{"a":0,"k":[0,0],"ix":2},"r":{"a":0,"k":0,"ix":6},"sa":{"a":0,"k":0,"ix":5},"o":{"a":0,"k":100,"ix":7}}]},{"ty":"gr","bm":0,"hd":false,"mn":"ADBE Vector Group","nm":"Group 5","ix":5,"cix":2,"np":2,"it":[{"ty":"sh","bm":0,"hd":false,"mn":"ADBE Vector Shape - Group","nm":"Path 1","ix":1,"d":1,"ks":{"a":0,"k":{"c":true,"i":[[3,1.937],[21.437,17.5],[6.937,6.5],[17.875,24.5],[0.687,21],[-2.438,-6.313],[-31.062,-31.813],[-6.063,-5.625],[-5.25,-2.875]],"o":[[0,0],[-6.063,-4.937],[-16.75,-15.5],[-6.562,-8.938],[-0.75,-21],[13.937,35.5],[6.75,6.937],[13.875,13.062],[3,1.937]],"v":[[38.732,71.718],[2.419,45.842],[-17.206,28.717],[-70.456,-31.157],[-91.456,-81.032],[-82.831,-96.532],[-2.081,13.906],[17.232,32.905],[47.607,57.968]]},"ix":2}},{"ty":"fl","bm":0,"hd":false,"mn":"ADBE Vector Graphic - Fill","nm":"Fill 1","c":{"a":0,"k":[0.9529,0.9451,0.9882],"ix":4},"r":1,"o":{"a":0,"k":100,"ix":5}},{"ty":"tr","a":{"a":0,"k":[0,0],"ix":1},"s":{"a":0,"k":[100,100],"ix":3},"sk":{"a":0,"k":0,"ix":4},"p":{"a":0,"k":[0,0],"ix":2},"r":{"a":0,"k":0,"ix":6},"sa":{"a":0,"k":0,"ix":5},"o":{"a":0,"k":100,"ix":7}}]},{"ty":"gr","bm":0,"hd":false,"mn":"ADBE Vector Group","nm":"Group 6","ix":6,"cix":2,"np":2,"it":[{"ty":"sh","bm":0,"hd":false,"mn":"ADBE Vector Shape - Group","nm":"Path 1","ix":1,"d":1,"ks":{"a":0,"k":{"c":true,"i":[[3.732,2.596],[-3.732,-2.596]],"o":[[-3.732,-2.596],[3.732,2.596]],"v":[[38.172,73.115],[48.493,57.083]]},"ix":2}},{"ty":"fl","bm":0,"hd":false,"mn":"ADBE Vector Graphic - Fill","nm":"Fill 1","c":{"a":0,"k":[0.6471,0.6471,0.6471],"ix":4},"r":1,"o":{"a":0,"k":100,"ix":5}},{"ty":"tr","a":{"a":0,"k":[0,0],"ix":1},"s":{"a":0,"k":[100,100],"ix":3},"sk":{"a":0,"k":0,"ix":4},"p":{"a":0,"k":[0,0],"ix":2},"r":{"a":0,"k":0,"ix":6},"sa":{"a":0,"k":0,"ix":5},"o":{"a":0,"k":100,"ix":7}}]},{"ty":"gr","bm":0,"hd":false,"mn":"ADBE Vector Group","nm":"Group 7","ix":7,"cix":2,"np":2,"it":[{"ty":"sh","bm":0,"hd":false,"mn":"ADBE Vector Shape - Group","nm":"Path 1","ix":1,"d":1,"ks":{"a":0,"k":{"c":true,"i":[[3.733,2.6],[0,0],[0,0],[-3.334,2.379],[0,0],[0,0],[0,0],[-0.048,-0.033]],"o":[[0,0],[0,0],[0.502,-3.865],[0,0],[0,0],[0,0],[0.052,0.03],[3.73,2.596]],"v":[[41.381,75.234],[38.324,73.208],[40.632,72.534],[48.517,59.846],[48.493,57.085],[51.54,59.105],[51.55,59.111],[51.703,59.205]]},"ix":2}},{"ty":"fl","bm":0,"hd":false,"mn":"ADBE Vector Graphic - Fill","nm":"Fill 1","c":{"a":0,"k":[0.7451,0.7451,0.7451],"ix":4},"r":1,"o":{"a":0,"k":100,"ix":5}},{"ty":"tr","a":{"a":0,"k":[0,0],"ix":1},"s":{"a":0,"k":[100,100],"ix":3},"sk":{"a":0,"k":0,"ix":4},"p":{"a":0,"k":[0,0],"ix":2},"r":{"a":0,"k":0,"ix":6},"sa":{"a":0,"k":0,"ix":5},"o":{"a":0,"k":100,"ix":7}}]},{"ty":"gr","bm":0,"hd":false,"mn":"ADBE Vector Group","nm":"Group 8","ix":8,"cix":2,"np":2,"it":[{"ty":"sh","bm":0,"hd":false,"mn":"ADBE Vector Shape - Group","nm":"Path 1","ix":1,"d":1,"ks":{"a":0,"k":{"c":true,"i":[[4.255,-6.792],[3.928,0.202],[-3.117,4.793],[3.95,2.477],[3.549,-2.773],[-2.919,-1.825]],"o":[[-3.404,5.442],[3.682,-0.35],[4.277,-6.58],[-2.649,-1.652],[3.769,-3.405],[4.042,2.527]],"v":[[53.216,71.97],[40.89,80.507],[52.079,72.303],[52.665,55.9],[42.602,57.953],[53.601,55.084]]},"ix":2}},{"ty":"fl","bm":0,"hd":false,"mn":"ADBE Vector Graphic - Fill","nm":"Fill 1","c":{"a":0,"k":[0.7451,0.7451,0.7451],"ix":4},"r":1,"o":{"a":0,"k":100,"ix":5}},{"ty":"tr","a":{"a":0,"k":[0,0],"ix":1},"s":{"a":0,"k":[100,100],"ix":3},"sk":{"a":0,"k":0,"ix":4},"p":{"a":0,"k":[0,0],"ix":2},"r":{"a":0,"k":0,"ix":6},"sa":{"a":0,"k":0,"ix":5},"o":{"a":0,"k":100,"ix":7}}]},{"ty":"gr","bm":0,"hd":false,"mn":"ADBE Vector Group","nm":"Group 9","ix":9,"cix":2,"np":2,"it":[{"ty":"sh","bm":0,"hd":false,"mn":"ADBE Vector Shape - Group","nm":"Path 1","ix":1,"d":1,"ks":{"a":0,"k":{"c":true,"i":[[-2.09,-1.309],[3.547,-5.924],[2.085,1.305],[-3.11,4.76]],"o":[[2.085,1.305],[-3.418,5.708],[-2.09,-1.309],[3.11,-4.76]],"v":[[52.022,58.517],[50.168,69.504],[40.759,75.755],[42.605,64.769]]},"ix":2}},{"ty":"fl","bm":0,"hd":false,"mn":"ADBE Vector Graphic - Fill","nm":"Fill 1","c":{"a":0,"k":[0.8,0.8,0.8],"ix":4},"r":1,"o":{"a":0,"k":100,"ix":5}},{"ty":"tr","a":{"a":0,"k":[0,0],"ix":1},"s":{"a":0,"k":[100,100],"ix":3},"sk":{"a":0,"k":0,"ix":4},"p":{"a":0,"k":[0,0],"ix":2},"r":{"a":0,"k":0,"ix":6},"sa":{"a":0,"k":0,"ix":5},"o":{"a":0,"k":100,"ix":7}}]},{"ty":"gr","bm":0,"hd":false,"mn":"ADBE Vector Group","nm":"Group 10","ix":10,"cix":2,"np":2,"it":[{"ty":"sh","bm":0,"hd":false,"mn":"ADBE Vector Shape - Group","nm":"Path 1","ix":1,"d":1,"ks":{"a":0,"k":{"c":true,"i":[[-4.048,-2.534],[4.253,-6.795],[4.038,2.528],[-4.253,6.795]],"o":[[4.038,2.528],[-4.253,6.795],[-4.048,-2.534],[4.253,-6.795]],"v":[[53.602,55.085],[53.218,71.972],[38.201,79.69],[38.571,62.803]]},"ix":2}},{"ty":"fl","bm":0,"hd":false,"mn":"ADBE Vector Graphic - Fill","nm":"Fill 1","c":{"a":0,"k":[0.9098,0.9098,0.9098],"ix":4},"r":1,"o":{"a":0,"k":100,"ix":5}},{"ty":"tr","a":{"a":0,"k":[0,0],"ix":1},"s":{"a":0,"k":[100,100],"ix":3},"sk":{"a":0,"k":0,"ix":4},"p":{"a":0,"k":[0,0],"ix":2},"r":{"a":0,"k":0,"ix":6},"sa":{"a":0,"k":0,"ix":5},"o":{"a":0,"k":100,"ix":7}}]},{"ty":"gr","bm":0,"hd":false,"mn":"ADBE Vector Group","nm":"Group 11","ix":11,"cix":2,"np":2,"it":[{"ty":"sh","bm":0,"hd":false,"mn":"ADBE Vector Shape - Group","nm":"Path 1","ix":1,"d":1,"ks":{"a":0,"k":{"c":true,"i":[[-0.295,-0.656],[-0.003,-0.005],[3.261,-5.205],[3.947,0.094],[1.638,2.699],[-0.453,-0.137],[-3.132,4.997],[-3.856,0.075],[0.135,0.443],[-1.36,-1.525]],"o":[[0.008,0.002],[1.59,3.496],[-3.433,5.487],[-2.597,-0.062],[0.481,0.06],[-1.351,-3.517],[3.268,-5.223],[-0.194,-0.385],[1.804,0.346],[0.452,0.507]],"v":[[57.645,58.958],[57.657,58.977],[55.131,73.333],[42.711,81.866],[36.387,77.802],[37.787,78.095],[40.484,64.166],[52.331,55.62],[51.835,54.382],[56.49,57.24]]},"ix":2}},{"ty":"fl","bm":0,"hd":false,"mn":"ADBE Vector Graphic - Fill","nm":"Fill 1","c":{"a":0,"k":[0.8,0.8,0.8],"ix":4},"r":1,"o":{"a":0,"k":100,"ix":5}},{"ty":"tr","a":{"a":0,"k":[0,0],"ix":1},"s":{"a":0,"k":[100,100],"ix":3},"sk":{"a":0,"k":0,"ix":4},"p":{"a":0,"k":[0,0],"ix":2},"r":{"a":0,"k":0,"ix":6},"sa":{"a":0,"k":0,"ix":5},"o":{"a":0,"k":100,"ix":7}}]},{"ty":"gr","bm":0,"hd":false,"mn":"ADBE Vector Group","nm":"Group 12","ix":12,"cix":2,"np":2,"it":[{"ty":"sh","bm":0,"hd":false,"mn":"ADBE Vector Shape - Group","nm":"Path 1","ix":1,"d":1,"ks":{"a":0,"k":{"c":true,"i":[[0.203,-1.399],[0,0],[0.526,0.731],[0.305,0.208],[0,0],[0,0]],"o":[[0,0],[0.14,-1.02],[-0.194,-0.275],[0,0],[0,0],[1.136,0.771]],"v":[[59.961,70.969],[57.562,69.432],[57.038,66.74],[56.29,66.006],[57.154,66.56],[58.696,67.545]]},"ix":2}},{"ty":"fl","bm":0,"hd":false,"mn":"ADBE Vector Graphic - Fill","nm":"Fill 1","c":{"a":0,"k":[0.7255,0.7255,0.7255],"ix":4},"r":1,"o":{"a":0,"k":100,"ix":5}},{"ty":"tr","a":{"a":0,"k":[0,0],"ix":1},"s":{"a":0,"k":[100,100],"ix":3},"sk":{"a":0,"k":0,"ix":4},"p":{"a":0,"k":[0,0],"ix":2},"r":{"a":0,"k":0,"ix":6},"sa":{"a":0,"k":0,"ix":5},"o":{"a":0,"k":100,"ix":7}}]},{"ty":"gr","bm":0,"hd":false,"mn":"ADBE Vector Group","nm":"Group 13","ix":13,"cix":2,"np":2,"it":[{"ty":"sh","bm":0,"hd":false,"mn":"ADBE Vector Shape - Group","nm":"Path 1","ix":1,"d":1,"ks":{"a":0,"k":{"c":true,"i":[[0.203,-1.399],[2.871,1.713],[0,0],[0,0],[-0.343,-0.028],[-0.505,3.614],[0.526,0.731],[0.305,0.208],[0,0],[0,0]],"o":[[-0.572,4.035],[0,0],[0,0],[0.307,0.181],[2.907,0.308],[0.14,-1.02],[-0.194,-0.275],[0,0],[0,0],[1.136,0.771]],"v":[[59.961,70.969],[51.513,78.519],[49.976,77.532],[49.146,77],[50.118,77.315],[57.562,69.432],[57.038,66.74],[56.29,66.006],[57.154,66.56],[58.696,67.545]]},"ix":2}},{"ty":"fl","bm":0,"hd":false,"mn":"ADBE Vector Graphic - Fill","nm":"Fill 1","c":{"a":0,"k":[0.8392,0.8392,0.8392],"ix":4},"r":1,"o":{"a":0,"k":100,"ix":5}},{"ty":"tr","a":{"a":0,"k":[0,0],"ix":1},"s":{"a":0,"k":[100,100],"ix":3},"sk":{"a":0,"k":0,"ix":4},"p":{"a":0,"k":[0,0],"ix":2},"r":{"a":0,"k":0,"ix":6},"sa":{"a":0,"k":0,"ix":5},"o":{"a":0,"k":100,"ix":7}}]},{"ty":"gr","bm":0,"hd":false,"mn":"ADBE Vector Group","nm":"Group 14","ix":14,"cix":2,"np":2,"it":[{"ty":"sh","bm":0,"hd":false,"mn":"ADBE Vector Shape - Group","nm":"Path 1","ix":1,"d":1,"ks":{"a":0,"k":{"c":true,"i":[[0.203,-1.399],[2.864,1.712],[0,0],[-0.554,4.043],[1.132,0.774],[0,0]],"o":[[-0.575,4.03],[0,0],[2.87,1.721],[0.196,-1.4],[0,0],[1.136,0.771]],"v":[[66.288,75.03],[57.846,82.577],[55.478,81.058],[63.887,73.488],[62.619,70.059],[65.024,71.606]]},"ix":2}},{"ty":"fl","bm":0,"hd":false,"mn":"ADBE Vector Graphic - Fill","nm":"Fill 1","c":{"a":0,"k":[0.8392,0.8392,0.8392],"ix":4},"r":1,"o":{"a":0,"k":100,"ix":5}},{"ty":"tr","a":{"a":0,"k":[0,0],"ix":1},"s":{"a":0,"k":[100,100],"ix":3},"sk":{"a":0,"k":0,"ix":4},"p":{"a":0,"k":[0,0],"ix":2},"r":{"a":0,"k":0,"ix":6},"sa":{"a":0,"k":0,"ix":5},"o":{"a":0,"k":100,"ix":7}}]},{"ty":"gr","bm":0,"hd":false,"mn":"ADBE Vector Group","nm":"Group 15","ix":15,"cix":2,"np":2,"it":[{"ty":"sh","bm":0,"hd":false,"mn":"ADBE Vector Shape - Group","nm":"Path 1","ix":1,"d":1,"ks":{"a":0,"k":{"c":true,"i":[[0.199,-1.396],[2.868,1.709],[0,0],[-0.559,4.046],[0,0],[1.132,0.774],[0,0]],"o":[[-0.58,4.033],[0,0],[2.871,1.713],[0,0],[0.199,-1.396],[0,0],[1.139,0.776]],"v":[[72.62,79.088],[64.173,86.638],[61.806,85.118],[70.219,77.546],[70.216,77.541],[68.947,74.12],[71.353,75.659]]},"ix":2}},{"ty":"fl","bm":0,"hd":false,"mn":"ADBE Vector Graphic - Fill","nm":"Fill 1","c":{"a":0,"k":[0.8392,0.8392,0.8392],"ix":4},"r":1,"o":{"a":0,"k":100,"ix":5}},{"ty":"tr","a":{"a":0,"k":[0,0],"ix":1},"s":{"a":0,"k":[100,100],"ix":3},"sk":{"a":0,"k":0,"ix":4},"p":{"a":0,"k":[0,0],"ix":2},"r":{"a":0,"k":0,"ix":6},"sa":{"a":0,"k":0,"ix":5},"o":{"a":0,"k":100,"ix":7}}]},{"ty":"gr","bm":0,"hd":false,"mn":"ADBE Vector Group","nm":"Group 16","ix":16,"cix":2,"np":2,"it":[{"ty":"sh","bm":0,"hd":false,"mn":"ADBE Vector Shape - Group","nm":"Path 1","ix":1,"d":1,"ks":{"a":0,"k":{"c":true,"i":[[0.203,-1.399],[2.871,1.713],[0,0],[-0.554,4.043],[1.132,0.774],[0,0]],"o":[[-0.568,4.032],[0,0],[2.871,1.713],[0.199,-1.396],[0,0],[1.136,0.771]],"v":[[78.945,83.144],[70.498,90.694],[68.134,89.179],[76.543,81.602],[75.274,78.18],[77.68,79.719]]},"ix":2}},{"ty":"fl","bm":0,"hd":false,"mn":"ADBE Vector Graphic - Fill","nm":"Fill 1","c":{"a":0,"k":[0.8392,0.8392,0.8392],"ix":4},"r":1,"o":{"a":0,"k":100,"ix":5}},{"ty":"tr","a":{"a":0,"k":[0,0],"ix":1},"s":{"a":0,"k":[100,100],"ix":3},"sk":{"a":0,"k":0,"ix":4},"p":{"a":0,"k":[0,0],"ix":2},"r":{"a":0,"k":0,"ix":6},"sa":{"a":0,"k":0,"ix":5},"o":{"a":0,"k":100,"ix":7}}]},{"ty":"gr","bm":0,"hd":false,"mn":"ADBE Vector Group","nm":"Group 17","ix":17,"cix":2,"np":2,"it":[{"ty":"sh","bm":0,"hd":false,"mn":"ADBE Vector Shape - Group","nm":"Path 1","ix":1,"d":1,"ks":{"a":0,"k":{"c":true,"i":[[2.094,-2.894],[1.304,1.401],[0.271,0.185],[0,0],[0.002,0.141],[0.621,0.422],[0,0],[0,0],[0,0],[0,0],[0.305,0.208],[0,0],[0,0],[0,0],[0,0],[0,0]],"o":[[0.689,-2.179],[-0.207,-0.227],[0,0],[0.019,-0.149],[0.007,-0.907],[0,0],[0,0],[0,0],[0,0],[-0.194,-0.275],[0,0],[0,0],[0,0],[0,0],[0,0],[2.43,1.653]],"v":[[84.224,91.916],[83.541,86.247],[82.823,85.629],[82.474,85.404],[82.501,84.972],[81.589,83.002],[57.809,67.745],[56.957,69.045],[55.951,68.402],[57.038,66.74],[56.29,66.006],[57.154,66.56],[57.456,66.102],[82.26,82.009],[82.263,82.014],[84.863,83.679]]},"ix":2}},{"ty":"fl","bm":0,"hd":false,"mn":"ADBE Vector Graphic - Fill","nm":"Fill 1","c":{"a":0,"k":[0.7255,0.7255,0.7255],"ix":4},"r":1,"o":{"a":0,"k":100,"ix":5}},{"ty":"tr","a":{"a":0,"k":[0,0],"ix":1},"s":{"a":0,"k":[100,100],"ix":3},"sk":{"a":0,"k":0,"ix":4},"p":{"a":0,"k":[0,0],"ix":2},"r":{"a":0,"k":0,"ix":6},"sa":{"a":0,"k":0,"ix":5},"o":{"a":0,"k":100,"ix":7}}]},{"ty":"gr","bm":0,"hd":false,"mn":"ADBE Vector Group","nm":"Group 18","ix":18,"cix":2,"np":2,"it":[{"ty":"sh","bm":0,"hd":false,"mn":"ADBE Vector Shape - Group","nm":"Path 1","ix":1,"d":1,"ks":{"a":0,"k":{"c":true,"i":[[2.094,-2.894],[2.049,1.222],[0,0],[-0.936,4.281],[1.365,0.932],[0,0]],"o":[[-2.018,2.793],[0,0],[2.979,1.779],[0.38,-1.722],[0,0],[2.43,1.653]],"v":[[84.224,91.916],[77.102,95.54],[74.544,93.899],[83.541,86.247],[82.263,82.014],[84.863,83.679]]},"ix":2}},{"ty":"fl","bm":0,"hd":false,"mn":"ADBE Vector Graphic - Fill","nm":"Fill 1","c":{"a":0,"k":[0.8392,0.8392,0.8392],"ix":4},"r":1,"o":{"a":0,"k":100,"ix":5}},{"ty":"tr","a":{"a":0,"k":[0,0],"ix":1},"s":{"a":0,"k":[100,100],"ix":3},"sk":{"a":0,"k":0,"ix":4},"p":{"a":0,"k":[0,0],"ix":2},"r":{"a":0,"k":0,"ix":6},"sa":{"a":0,"k":0,"ix":5},"o":{"a":0,"k":100,"ix":7}}]},{"ty":"gr","bm":0,"hd":false,"mn":"ADBE Vector Group","nm":"Group 19","ix":19,"cix":2,"np":2,"it":[{"ty":"sh","bm":0,"hd":false,"mn":"ADBE Vector Shape - Group","nm":"Path 1","ix":1,"d":1,"ks":{"a":0,"k":{"c":true,"i":[[2.416,-1.588],[0.87,0.52],[0,0],[0,0],[0,0],[0.008,-0.903]],"o":[[-0.66,0.434],[0,0],[0,0],[0,0],[0.621,0.424],[-0.021,2.322]],"v":[[77.925,92.311],[75.156,92.875],[51.352,77.609],[57.807,67.744],[81.59,82.998],[82.5,84.971]]},"ix":2}},{"ty":"fl","bm":0,"hd":false,"mn":"ADBE Vector Graphic - Fill","nm":"Fill 1","c":{"a":0,"k":[0.7255,0.7255,0.7255],"ix":4},"r":1,"o":{"a":0,"k":100,"ix":5}},{"ty":"tr","a":{"a":0,"k":[0,0],"ix":1},"s":{"a":0,"k":[100,100],"ix":3},"sk":{"a":0,"k":0,"ix":4},"p":{"a":0,"k":[0,0],"ix":2},"r":{"a":0,"k":0,"ix":6},"sa":{"a":0,"k":0,"ix":5},"o":{"a":0,"k":100,"ix":7}}]},{"ty":"gr","bm":0,"hd":false,"mn":"ADBE Vector Group","nm":"Group 20","ix":20,"cix":2,"np":2,"it":[{"ty":"sh","bm":0,"hd":false,"mn":"ADBE Vector Shape - Group","nm":"Path 1","ix":1,"d":1,"ks":{"a":0,"k":{"c":true,"i":[[0.38,-1.722],[2.979,1.779],[0,0],[0,0],[0,0],[0,0],[0,0],[0,0],[0,0],[0,0],[0,0]],"o":[[-0.936,4.281],[0,0],[0,0],[0,0],[0,0],[0,0],[0,0],[0,0],[0,0],[0,0],[1.365,0.932]],"v":[[83.541,86.247],[74.544,93.899],[49.695,77.963],[49.976,77.532],[50.118,77.315],[55.951,68.402],[57.038,66.74],[57.154,66.56],[57.456,66.102],[82.26,82.009],[82.263,82.014]]},"ix":2}},{"ty":"fl","bm":0,"hd":false,"mn":"ADBE Vector Graphic - Fill","nm":"Fill 1","c":{"a":0,"k":[0.8392,0.8392,0.8392],"ix":4},"r":1,"o":{"a":0,"k":100,"ix":5}},{"ty":"tr","a":{"a":0,"k":[0,0],"ix":1},"s":{"a":0,"k":[100,100],"ix":3},"sk":{"a":0,"k":0,"ix":4},"p":{"a":0,"k":[0,0],"ix":2},"r":{"a":0,"k":0,"ix":6},"sa":{"a":0,"k":0,"ix":5},"o":{"a":0,"k":100,"ix":7}}]},{"ty":"gr","bm":0,"hd":false,"mn":"ADBE Vector Group","nm":"Group 21","ix":21,"cix":2,"np":2,"it":[{"ty":"sh","bm":0,"hd":false,"mn":"ADBE Vector Shape - Group","nm":"Path 1","ix":1,"d":1,"ks":{"a":0,"k":{"c":true,"i":[[5.362,3.203],[0,0],[4.066,2.771],[0,0],[0,0],[0,0]],"o":[[0,0],[4.288,-3.603],[0,0],[0,0],[0,0],[6.124,4.175]],"v":[[79.728,99.535],[79.237,99.222],[82.823,85.629],[51.856,65.774],[54.5,61.733],[89.697,84.303]]},"ix":2}},{"ty":"fl","bm":0,"hd":false,"mn":"ADBE Vector Graphic - Fill","nm":"Fill 1","c":{"a":0,"k":[0.6745,0.6745,0.6745],"ix":4},"r":1,"o":{"a":0,"k":100,"ix":5}},{"ty":"tr","a":{"a":0,"k":[0,0],"ix":1},"s":{"a":0,"k":[100,100],"ix":3},"sk":{"a":0,"k":0,"ix":4},"p":{"a":0,"k":[0,0],"ix":2},"r":{"a":0,"k":0,"ix":6},"sa":{"a":0,"k":0,"ix":5},"o":{"a":0,"k":100,"ix":7}}]},{"ty":"gr","bm":0,"hd":false,"mn":"ADBE Vector Group","nm":"Group 22","ix":22,"cix":2,"np":2,"it":[{"ty":"sh","bm":0,"hd":false,"mn":"ADBE Vector Shape - Group","nm":"Path 1","ix":1,"d":1,"ks":{"a":0,"k":{"c":true,"i":[[5.362,3.203],[0,0],[0,0],[0,0]],"o":[[0,0],[0,0],[0,0],[6.124,4.175]],"v":[[79.728,99.535],[44.53,76.965],[54.5,61.733],[89.697,84.303]]},"ix":2}},{"ty":"fl","bm":0,"hd":false,"mn":"ADBE Vector Graphic - Fill","nm":"Fill 1","c":{"a":0,"k":[0.7255,0.7255,0.7255],"ix":4},"r":1,"o":{"a":0,"k":100,"ix":5}},{"ty":"tr","a":{"a":0,"k":[0,0],"ix":1},"s":{"a":0,"k":[100,100],"ix":3},"sk":{"a":0,"k":0,"ix":4},"p":{"a":0,"k":[0,0],"ix":2},"r":{"a":0,"k":0,"ix":6},"sa":{"a":0,"k":0,"ix":5},"o":{"a":0,"k":100,"ix":7}}]}],"ind":4,"parent":7},{"ty":4,"nm":"Layer 3","sr":1,"st":0,"op":20,"ip":0,"hd":false,"ddd":0,"bm":0,"tt":1,"hasMask":false,"ao":0,"ks":{"a":{"a":0,"k":[0,0,0],"ix":1},"s":{"a":0,"k":[100,100,100],"ix":6},"sk":{"a":0,"k":0},"p":{"a":1,"k":[{"o":{"x":0.167,"y":0.167},"i":{"x":0.833,"y":0.833},"s":[40.946,74.411,0],"t":0,"ti":[31.761,16.322,0],"to":[-31.761,-16.322,0]},{"s":[-149.619,-23.523,0],"t":20}],"ix":2},"r":{"a":0,"k":-5,"ix":10},"sa":{"a":0,"k":0},"o":{"a":0,"k":48,"ix":11}},"ef":[],"shapes":[{"ty":"gr","bm":0,"hd":false,"mn":"ADBE Vector Group","nm":"Group 1","ix":1,"cix":2,"np":2,"it":[{"ty":"sh","bm":0,"hd":false,"mn":"ADBE Vector Shape - Group","nm":"Path 1","ix":1,"d":1,"ks":{"a":0,"k":{"c":true,"i":[[0,0],[0,0],[0,0],[0,0]],"o":[[0,0],[0,0],[0,0],[0,0]],"v":[[11.08,118.796],[7.044,118.796],[7.044,-136.857],[11.08,-136.857]]},"ix":2}},{"ty":"fl","bm":0,"hd":false,"mn":"ADBE Vector Graphic - Fill","nm":"Fill 1","c":{"a":0,"k":[1,1,1],"ix":4},"r":1,"o":{"a":0,"k":100,"ix":5}},{"ty":"tr","a":{"a":0,"k":[0,0],"ix":1},"s":{"a":0,"k":[100,100],"ix":3},"sk":{"a":0,"k":0,"ix":4},"p":{"a":0,"k":[0,0],"ix":2},"r":{"a":0,"k":0,"ix":6},"sa":{"a":0,"k":0,"ix":5},"o":{"a":0,"k":100,"ix":7}}]},{"ty":"gr","bm":0,"hd":false,"mn":"ADBE Vector Group","nm":"Group 2","ix":2,"cix":2,"np":2,"it":[{"ty":"sh","bm":0,"hd":false,"mn":"ADBE Vector Shape - Group","nm":"Path 1","ix":1,"d":1,"ks":{"a":0,"k":{"c":true,"i":[[0,0],[0,0],[0,0],[0,0]],"o":[[0,0],[0,0],[0,0],[0,0]],"v":[[-0.221,118.796],[-16.031,118.796],[-16.031,-136.857],[-0.221,-136.857]]},"ix":2}},{"ty":"fl","bm":0,"hd":false,"mn":"ADBE Vector Graphic - Fill","nm":"Fill 1","c":{"a":0,"k":[1,1,1],"ix":4},"r":1,"o":{"a":0,"k":100,"ix":5}},{"ty":"tr","a":{"a":0,"k":[0,0],"ix":1},"s":{"a":0,"k":[100,100],"ix":3},"sk":{"a":0,"k":0,"ix":4},"p":{"a":0,"k":[0,0],"ix":2},"r":{"a":0,"k":0,"ix":6},"sa":{"a":0,"k":0,"ix":5},"o":{"a":0,"k":100,"ix":7}}]}],"ind":5,"parent":7},{"ty":4,"nm":"Layer 1","sr":1,"st":0,"op":125,"ip":0,"hd":false,"ddd":0,"bm":0,"hasMask":false,"ao":0,"ks":{"a":{"a":0,"k":[-48.876,71.657,0],"ix":1},"s":{"a":0,"k":[100,100,100],"ix":6},"sk":{"a":0,"k":0},"p":{"a":1,"k":[{"o":{"x":0.333,"y":0},"i":{"x":0.407,"y":1},"s":[1.124,121.657,0],"t":3,"ti":[0,0,0],"to":[0,-3.333,0]},{"o":{"x":0.606,"y":0},"i":{"x":0.667,"y":1},"s":[1.124,101.657,0],"t":13,"ti":[0,-3.333,0],"to":[0,0,0]},{"o":{"x":0.167,"y":0.167},"i":{"x":0.833,"y":0.833},"s":[1.124,121.657,0],"t":23,"ti":[0,0,0],"to":[0,0,0]},{"o":{"x":0.167,"y":0.167},"i":{"x":0.833,"y":0.833},"s":[1.124,121.657,0],"t":55,"ti":[0,0,0],"to":[6.333,-2.5,0]},{"o":{"x":0.167,"y":0.167},"i":{"x":0.833,"y":1},"s":[39.124,106.657,0],"t":60,"ti":[6.333,-2.5,0],"to":[0,0,0]},{"s":[1.124,121.657,0],"t":66}],"ix":2},"r":{"a":1,"k":[{"o":{"x":0.167,"y":0.167},"i":{"x":0.833,"y":0.833},"s":[-45],"t":30},{"o":{"x":0.167,"y":0.167},"i":{"x":0.833,"y":0.833},"s":[-65],"t":35},{"o":{"x":0.167,"y":0.167},"i":{"x":0.833,"y":0.833},"s":[-35],"t":40},{"o":{"x":0.167,"y":0.167},"i":{"x":0.833,"y":0.833},"s":[-37],"t":45},{"o":{"x":0.167,"y":0.167},"i":{"x":0.833,"y":0.833},"s":[-59],"t":50},{"o":{"x":0.167,"y":0.167},"i":{"x":0.833,"y":0.833},"s":[-21],"t":55},{"o":{"x":0.167,"y":0.167},"i":{"x":0.667,"y":1},"s":[-18],"t":60},{"o":{"x":0.333,"y":0},"i":{"x":0.667,"y":1},"s":[-45],"t":66},{"o":{"x":0.333,"y":0},"i":{"x":0.667,"y":1},"s":[-15],"t":73},{"s":[-45],"t":80}],"ix":10},"sa":{"a":0,"k":0},"o":{"a":0,"k":100,"ix":11}},"ef":[],"shapes":[{"ty":"gr","bm":0,"hd":false,"mn":"ADBE Vector Group","nm":"Group 1","ix":1,"cix":2,"np":2,"it":[{"ty":"sh","bm":0,"hd":false,"mn":"ADBE Vector Shape - Group","nm":"Path 1","ix":1,"d":1,"ks":{"a":0,"k":{"c":true,"i":[[-0.203,-1.399],[0,0],[-1.132,0.774],[0,0]],"o":[[0,0],[-0.199,-1.396],[0,0],[-1.136,0.771]],"v":[[-78.945,83.144],[-76.543,81.602],[-75.274,78.18],[-77.68,79.719]]},"ix":2}},{"ty":"fl","bm":0,"hd":false,"mn":"ADBE Vector Graphic - Fill","nm":"Fill 1","c":{"a":0,"k":[0.7255,0.7255,0.7255],"ix":4},"r":1,"o":{"a":0,"k":100,"ix":5}},{"ty":"tr","a":{"a":0,"k":[0,0],"ix":1},"s":{"a":0,"k":[100,100],"ix":3},"sk":{"a":0,"k":0,"ix":4},"p":{"a":0,"k":[0,0],"ix":2},"r":{"a":0,"k":0,"ix":6},"sa":{"a":0,"k":0,"ix":5},"o":{"a":0,"k":100,"ix":7}}]},{"ty":"gr","bm":0,"hd":false,"mn":"ADBE Vector Group","nm":"Group 2","ix":2,"cix":2,"np":2,"it":[{"ty":"sh","bm":0,"hd":false,"mn":"ADBE Vector Shape - Group","nm":"Path 1","ix":1,"d":1,"ks":{"a":0,"k":{"c":true,"i":[[0,0],[-0.199,-1.396],[0,0],[0,0],[-1.132,0.774]],"o":[[-1.139,0.776],[0,0],[0,0],[-0.199,-1.396],[0,0]],"v":[[-71.353,75.659],[-72.62,79.088],[-70.219,77.546],[-70.216,77.541],[-68.947,74.12]]},"ix":2}},{"ty":"fl","bm":0,"hd":false,"mn":"ADBE Vector Graphic - Fill","nm":"Fill 1","c":{"a":0,"k":[0.7255,0.7255,0.7255],"ix":4},"r":1,"o":{"a":0,"k":100,"ix":5}},{"ty":"tr","a":{"a":0,"k":[0,0],"ix":1},"s":{"a":0,"k":[100,100],"ix":3},"sk":{"a":0,"k":0,"ix":4},"p":{"a":0,"k":[0,0],"ix":2},"r":{"a":0,"k":0,"ix":6},"sa":{"a":0,"k":0,"ix":5},"o":{"a":0,"k":100,"ix":7}}]},{"ty":"gr","bm":0,"hd":false,"mn":"ADBE Vector Group","nm":"Group 3","ix":3,"cix":2,"np":2,"it":[{"ty":"sh","bm":0,"hd":false,"mn":"ADBE Vector Shape - Group","nm":"Path 1","ix":1,"d":1,"ks":{"a":0,"k":{"c":true,"i":[[0,0],[-0.203,-1.399],[0,0],[-1.132,0.774]],"o":[[-1.136,0.771],[0,0],[-0.196,-1.4],[0,0]],"v":[[-65.024,71.606],[-66.288,75.03],[-63.887,73.488],[-62.619,70.059]]},"ix":2}},{"ty":"fl","bm":0,"hd":false,"mn":"ADBE Vector Graphic - Fill","nm":"Fill 1","c":{"a":0,"k":[0.7255,0.7255,0.7255],"ix":4},"r":1,"o":{"a":0,"k":100,"ix":5}},{"ty":"tr","a":{"a":0,"k":[0,0],"ix":1},"s":{"a":0,"k":[100,100],"ix":3},"sk":{"a":0,"k":0,"ix":4},"p":{"a":0,"k":[0,0],"ix":2},"r":{"a":0,"k":0,"ix":6},"sa":{"a":0,"k":0,"ix":5},"o":{"a":0,"k":100,"ix":7}}]},{"ty":"gr","bm":0,"hd":false,"mn":"ADBE Vector Group","nm":"Group 4","ix":4,"cix":2,"np":2,"it":[{"ty":"sh","bm":0,"hd":false,"mn":"ADBE Vector Shape - Group","nm":"Path 1","ix":1,"d":1,"ks":{"a":0,"k":{"c":true,"i":[[-2.933,1.887],[-51.48,70.352],[-0.701,21.006],[0.059,1.648],[0.021,-0.693],[6.539,-8.943],[0,0],[1.549,4.612]],"o":[[0,0],[6.539,-8.943],[0.067,-2.006],[-0.006,0.651],[-0.701,21.006],[-51.48,70.352],[-2.197,1.417],[-2.304,2.508]],"v":[[-38.728,71.71],[70.476,-31.156],[91.481,-81.05],[91.487,-86.528],[91.442,-84.514],[70.437,-34.62],[-38.767,68.246],[-47.802,58.136]]},"ix":2}},{"ty":"fl","bm":0,"hd":false,"mn":"ADBE Vector Graphic - Fill","nm":"Fill 1","c":{"a":0,"k":[0.8157,0.8078,0.949],"ix":4},"r":1,"o":{"a":0,"k":100,"ix":5}},{"ty":"tr","a":{"a":0,"k":[0,0],"ix":1},"s":{"a":0,"k":[100,100],"ix":3},"sk":{"a":0,"k":0,"ix":4},"p":{"a":0,"k":[0,0],"ix":2},"r":{"a":0,"k":0,"ix":6},"sa":{"a":0,"k":0,"ix":5},"o":{"a":0,"k":100,"ix":7}}]},{"ty":"gr","bm":0,"hd":false,"mn":"ADBE Vector Group","nm":"Group 5","ix":5,"cix":2,"np":2,"it":[{"ty":"sh","bm":0,"hd":false,"mn":"ADBE Vector Shape - Group","nm":"Path 1","ix":1,"d":1,"ks":{"a":0,"k":{"c":true,"i":[[17.905,-9.861],[-3.016,1.94],[-51.48,70.352],[-0.701,21.006],[2.462,-6.283]],"o":[[-3.016,1.94],[0,0],[6.539,-8.943],[0.704,-21.01],[-23.908,61.032]],"v":[[-47.579,57.945],[-38.728,71.71],[70.476,-31.156],[91.481,-81.05],[82.828,-96.559]]},"ix":2}},{"ty":"fl","bm":0,"hd":false,"mn":"ADBE Vector Graphic - Fill","nm":"Fill 1","c":{"a":0,"k":[0.9529,0.9451,0.9882],"ix":4},"r":1,"o":{"a":0,"k":100,"ix":5}},{"ty":"tr","a":{"a":0,"k":[0,0],"ix":1},"s":{"a":0,"k":[100,100],"ix":3},"sk":{"a":0,"k":0,"ix":4},"p":{"a":0,"k":[0,0],"ix":2},"r":{"a":0,"k":0,"ix":6},"sa":{"a":0,"k":0,"ix":5},"o":{"a":0,"k":100,"ix":7}}]},{"ty":"gr","bm":0,"hd":false,"mn":"ADBE Vector Group","nm":"Group 6","ix":6,"cix":2,"np":2,"it":[{"ty":"sh","bm":0,"hd":false,"mn":"ADBE Vector Shape - Group","nm":"Path 1","ix":1,"d":1,"ks":{"a":0,"k":{"c":true,"i":[[-3.732,2.596],[3.732,-2.596]],"o":[[3.732,-2.596],[-3.732,2.596]],"v":[[-38.172,73.115],[-48.493,57.083]]},"ix":2}},{"ty":"fl","bm":0,"hd":false,"mn":"ADBE Vector Graphic - Fill","nm":"Fill 1","c":{"a":0,"k":[0.6471,0.6471,0.6471],"ix":4},"r":1,"o":{"a":0,"k":100,"ix":5}},{"ty":"tr","a":{"a":0,"k":[0,0],"ix":1},"s":{"a":0,"k":[100,100],"ix":3},"sk":{"a":0,"k":0,"ix":4},"p":{"a":0,"k":[0,0],"ix":2},"r":{"a":0,"k":0,"ix":6},"sa":{"a":0,"k":0,"ix":5},"o":{"a":0,"k":100,"ix":7}}]},{"ty":"gr","bm":0,"hd":false,"mn":"ADBE Vector Group","nm":"Group 7","ix":7,"cix":2,"np":2,"it":[{"ty":"sh","bm":0,"hd":false,"mn":"ADBE Vector Shape - Group","nm":"Path 1","ix":1,"d":1,"ks":{"a":0,"k":{"c":true,"i":[[-3.733,2.6],[0,0],[0,0],[3.334,2.379],[0,0],[0,0],[0,0],[0.048,-0.033]],"o":[[0,0],[0,0],[-0.502,-3.865],[0,0],[0,0],[0,0],[-0.052,0.03],[-3.73,2.596]],"v":[[-41.381,75.234],[-38.324,73.208],[-40.632,72.534],[-48.517,59.846],[-48.493,57.085],[-51.54,59.105],[-51.55,59.111],[-51.703,59.205]]},"ix":2}},{"ty":"fl","bm":0,"hd":false,"mn":"ADBE Vector Graphic - Fill","nm":"Fill 1","c":{"a":0,"k":[0.7451,0.7451,0.7451],"ix":4},"r":1,"o":{"a":0,"k":100,"ix":5}},{"ty":"tr","a":{"a":0,"k":[0,0],"ix":1},"s":{"a":0,"k":[100,100],"ix":3},"sk":{"a":0,"k":0,"ix":4},"p":{"a":0,"k":[0,0],"ix":2},"r":{"a":0,"k":0,"ix":6},"sa":{"a":0,"k":0,"ix":5},"o":{"a":0,"k":100,"ix":7}}]},{"ty":"gr","bm":0,"hd":false,"mn":"ADBE Vector Group","nm":"Group 8","ix":8,"cix":2,"np":2,"it":[{"ty":"sh","bm":0,"hd":false,"mn":"ADBE Vector Shape - Group","nm":"Path 1","ix":1,"d":1,"ks":{"a":0,"k":{"c":true,"i":[[-4.255,-6.792],[-3.928,0.202],[3.117,4.793],[-3.95,2.477],[-3.549,-2.773],[2.919,-1.825]],"o":[[3.404,5.442],[-3.682,-0.35],[-4.277,-6.58],[2.649,-1.652],[-3.769,-3.405],[-4.042,2.527]],"v":[[-53.216,71.97],[-40.89,80.507],[-52.079,72.303],[-52.665,55.9],[-42.602,57.953],[-53.601,55.084]]},"ix":2}},{"ty":"fl","bm":0,"hd":false,"mn":"ADBE Vector Graphic - Fill","nm":"Fill 1","c":{"a":0,"k":[0.7451,0.7451,0.7451],"ix":4},"r":1,"o":{"a":0,"k":100,"ix":5}},{"ty":"tr","a":{"a":0,"k":[0,0],"ix":1},"s":{"a":0,"k":[100,100],"ix":3},"sk":{"a":0,"k":0,"ix":4},"p":{"a":0,"k":[0,0],"ix":2},"r":{"a":0,"k":0,"ix":6},"sa":{"a":0,"k":0,"ix":5},"o":{"a":0,"k":100,"ix":7}}]},{"ty":"gr","bm":0,"hd":false,"mn":"ADBE Vector Group","nm":"Group 9","ix":9,"cix":2,"np":2,"it":[{"ty":"sh","bm":0,"hd":false,"mn":"ADBE Vector Shape - Group","nm":"Path 1","ix":1,"d":1,"ks":{"a":0,"k":{"c":true,"i":[[2.09,-1.309],[-3.547,-5.924],[-2.085,1.305],[3.11,4.76]],"o":[[-2.085,1.305],[3.418,5.708],[2.09,-1.309],[-3.11,-4.76]],"v":[[-52.022,58.517],[-50.168,69.504],[-40.759,75.755],[-42.605,64.769]]},"ix":2}},{"ty":"fl","bm":0,"hd":false,"mn":"ADBE Vector Graphic - Fill","nm":"Fill 1","c":{"a":0,"k":[0.8,0.8,0.8],"ix":4},"r":1,"o":{"a":0,"k":100,"ix":5}},{"ty":"tr","a":{"a":0,"k":[0,0],"ix":1},"s":{"a":0,"k":[100,100],"ix":3},"sk":{"a":0,"k":0,"ix":4},"p":{"a":0,"k":[0,0],"ix":2},"r":{"a":0,"k":0,"ix":6},"sa":{"a":0,"k":0,"ix":5},"o":{"a":0,"k":100,"ix":7}}]},{"ty":"gr","bm":0,"hd":false,"mn":"ADBE Vector Group","nm":"Group 10","ix":10,"cix":2,"np":2,"it":[{"ty":"sh","bm":0,"hd":false,"mn":"ADBE Vector Shape - Group","nm":"Path 1","ix":1,"d":1,"ks":{"a":0,"k":{"c":true,"i":[[4.048,-2.534],[-4.253,-6.795],[-4.038,2.528],[4.253,6.795]],"o":[[-4.038,2.528],[4.253,6.795],[4.048,-2.534],[-4.253,-6.795]],"v":[[-53.602,55.085],[-53.218,71.972],[-38.201,79.69],[-38.571,62.803]]},"ix":2}},{"ty":"fl","bm":0,"hd":false,"mn":"ADBE Vector Graphic - Fill","nm":"Fill 1","c":{"a":0,"k":[0.9098,0.9098,0.9098],"ix":4},"r":1,"o":{"a":0,"k":100,"ix":5}},{"ty":"tr","a":{"a":0,"k":[0,0],"ix":1},"s":{"a":0,"k":[100,100],"ix":3},"sk":{"a":0,"k":0,"ix":4},"p":{"a":0,"k":[0,0],"ix":2},"r":{"a":0,"k":0,"ix":6},"sa":{"a":0,"k":0,"ix":5},"o":{"a":0,"k":100,"ix":7}}]},{"ty":"gr","bm":0,"hd":false,"mn":"ADBE Vector Group","nm":"Group 11","ix":11,"cix":2,"np":2,"it":[{"ty":"sh","bm":0,"hd":false,"mn":"ADBE Vector Shape - Group","nm":"Path 1","ix":1,"d":1,"ks":{"a":0,"k":{"c":true,"i":[[0.295,-0.656],[0.003,-0.005],[-3.261,-5.205],[-3.947,0.094],[-1.638,2.699],[0.453,-0.137],[3.132,4.997],[3.856,0.075],[-0.135,0.443],[1.36,-1.525]],"o":[[-0.008,0.002],[-1.59,3.496],[3.433,5.487],[2.597,-0.062],[-0.481,0.06],[1.351,-3.517],[-3.268,-5.223],[0.194,-0.385],[-1.804,0.346],[-0.452,0.507]],"v":[[-57.645,58.958],[-57.657,58.977],[-55.131,73.333],[-42.711,81.866],[-36.387,77.802],[-37.787,78.095],[-40.484,64.166],[-52.331,55.62],[-51.835,54.382],[-56.49,57.24]]},"ix":2}},{"ty":"fl","bm":0,"hd":false,"mn":"ADBE Vector Graphic - Fill","nm":"Fill 1","c":{"a":0,"k":[0.8,0.8,0.8],"ix":4},"r":1,"o":{"a":0,"k":100,"ix":5}},{"ty":"tr","a":{"a":0,"k":[0,0],"ix":1},"s":{"a":0,"k":[100,100],"ix":3},"sk":{"a":0,"k":0,"ix":4},"p":{"a":0,"k":[0,0],"ix":2},"r":{"a":0,"k":0,"ix":6},"sa":{"a":0,"k":0,"ix":5},"o":{"a":0,"k":100,"ix":7}}]},{"ty":"gr","bm":0,"hd":false,"mn":"ADBE Vector Group","nm":"Group 12","ix":12,"cix":2,"np":2,"it":[{"ty":"sh","bm":0,"hd":false,"mn":"ADBE Vector Shape - Group","nm":"Path 1","ix":1,"d":1,"ks":{"a":0,"k":{"c":true,"i":[[-0.203,-1.399],[0,0],[-0.526,0.731],[-0.305,0.208],[0,0],[0,0]],"o":[[0,0],[-0.14,-1.02],[0.194,-0.275],[0,0],[0,0],[-1.136,0.771]],"v":[[-59.961,70.969],[-57.562,69.432],[-57.038,66.74],[-56.29,66.006],[-57.154,66.56],[-58.696,67.545]]},"ix":2}},{"ty":"fl","bm":0,"hd":false,"mn":"ADBE Vector Graphic - Fill","nm":"Fill 1","c":{"a":0,"k":[0.7255,0.7255,0.7255],"ix":4},"r":1,"o":{"a":0,"k":100,"ix":5}},{"ty":"tr","a":{"a":0,"k":[0,0],"ix":1},"s":{"a":0,"k":[100,100],"ix":3},"sk":{"a":0,"k":0,"ix":4},"p":{"a":0,"k":[0,0],"ix":2},"r":{"a":0,"k":0,"ix":6},"sa":{"a":0,"k":0,"ix":5},"o":{"a":0,"k":100,"ix":7}}]},{"ty":"gr","bm":0,"hd":false,"mn":"ADBE Vector Group","nm":"Group 13","ix":13,"cix":2,"np":2,"it":[{"ty":"sh","bm":0,"hd":false,"mn":"ADBE Vector Shape - Group","nm":"Path 1","ix":1,"d":1,"ks":{"a":0,"k":{"c":true,"i":[[-0.203,-1.399],[-2.871,1.713],[0,0],[0,0],[0.343,-0.028],[0.505,3.614],[-0.526,0.731],[-0.305,0.208],[0,0],[0,0]],"o":[[0.572,4.035],[0,0],[0,0],[-0.307,0.181],[-2.907,0.308],[-0.14,-1.02],[0.194,-0.275],[0,0],[0,0],[-1.136,0.771]],"v":[[-59.961,70.969],[-51.513,78.519],[-49.976,77.532],[-49.146,77],[-50.118,77.315],[-57.562,69.432],[-57.038,66.74],[-56.29,66.006],[-57.154,66.56],[-58.696,67.545]]},"ix":2}},{"ty":"fl","bm":0,"hd":false,"mn":"ADBE Vector Graphic - Fill","nm":"Fill 1","c":{"a":0,"k":[0.8392,0.8392,0.8392],"ix":4},"r":1,"o":{"a":0,"k":100,"ix":5}},{"ty":"tr","a":{"a":0,"k":[0,0],"ix":1},"s":{"a":0,"k":[100,100],"ix":3},"sk":{"a":0,"k":0,"ix":4},"p":{"a":0,"k":[0,0],"ix":2},"r":{"a":0,"k":0,"ix":6},"sa":{"a":0,"k":0,"ix":5},"o":{"a":0,"k":100,"ix":7}}]},{"ty":"gr","bm":0,"hd":false,"mn":"ADBE Vector Group","nm":"Group 14","ix":14,"cix":2,"np":2,"it":[{"ty":"sh","bm":0,"hd":false,"mn":"ADBE Vector Shape - Group","nm":"Path 1","ix":1,"d":1,"ks":{"a":0,"k":{"c":true,"i":[[-0.203,-1.399],[-2.864,1.712],[0,0],[0.554,4.043],[-1.132,0.774],[0,0]],"o":[[0.575,4.03],[0,0],[-2.87,1.721],[-0.196,-1.4],[0,0],[-1.136,0.771]],"v":[[-66.288,75.03],[-57.846,82.577],[-55.478,81.058],[-63.887,73.488],[-62.619,70.059],[-65.024,71.606]]},"ix":2}},{"ty":"fl","bm":0,"hd":false,"mn":"ADBE Vector Graphic - Fill","nm":"Fill 1","c":{"a":0,"k":[0.8392,0.8392,0.8392],"ix":4},"r":1,"o":{"a":0,"k":100,"ix":5}},{"ty":"tr","a":{"a":0,"k":[0,0],"ix":1},"s":{"a":0,"k":[100,100],"ix":3},"sk":{"a":0,"k":0,"ix":4},"p":{"a":0,"k":[0,0],"ix":2},"r":{"a":0,"k":0,"ix":6},"sa":{"a":0,"k":0,"ix":5},"o":{"a":0,"k":100,"ix":7}}]},{"ty":"gr","bm":0,"hd":false,"mn":"ADBE Vector Group","nm":"Group 15","ix":15,"cix":2,"np":2,"it":[{"ty":"sh","bm":0,"hd":false,"mn":"ADBE Vector Shape - Group","nm":"Path 1","ix":1,"d":1,"ks":{"a":0,"k":{"c":true,"i":[[-0.199,-1.396],[-2.868,1.709],[0,0],[0.559,4.046],[0,0],[-1.132,0.774],[0,0]],"o":[[0.58,4.033],[0,0],[-2.871,1.713],[0,0],[-0.199,-1.396],[0,0],[-1.139,0.776]],"v":[[-72.62,79.088],[-64.173,86.638],[-61.806,85.118],[-70.219,77.546],[-70.216,77.541],[-68.947,74.12],[-71.353,75.659]]},"ix":2}},{"ty":"fl","bm":0,"hd":false,"mn":"ADBE Vector Graphic - Fill","nm":"Fill 1","c":{"a":0,"k":[0.8392,0.8392,0.8392],"ix":4},"r":1,"o":{"a":0,"k":100,"ix":5}},{"ty":"tr","a":{"a":0,"k":[0,0],"ix":1},"s":{"a":0,"k":[100,100],"ix":3},"sk":{"a":0,"k":0,"ix":4},"p":{"a":0,"k":[0,0],"ix":2},"r":{"a":0,"k":0,"ix":6},"sa":{"a":0,"k":0,"ix":5},"o":{"a":0,"k":100,"ix":7}}]},{"ty":"gr","bm":0,"hd":false,"mn":"ADBE Vector Group","nm":"Group 16","ix":16,"cix":2,"np":2,"it":[{"ty":"sh","bm":0,"hd":false,"mn":"ADBE Vector Shape - Group","nm":"Path 1","ix":1,"d":1,"ks":{"a":0,"k":{"c":true,"i":[[-0.203,-1.399],[-2.871,1.713],[0,0],[0.554,4.043],[-1.132,0.774],[0,0]],"o":[[0.568,4.032],[0,0],[-2.871,1.713],[-0.199,-1.396],[0,0],[-1.136,0.771]],"v":[[-78.945,83.144],[-70.498,90.694],[-68.134,89.179],[-76.543,81.602],[-75.274,78.18],[-77.68,79.719]]},"ix":2}},{"ty":"fl","bm":0,"hd":false,"mn":"ADBE Vector Graphic - Fill","nm":"Fill 1","c":{"a":0,"k":[0.8392,0.8392,0.8392],"ix":4},"r":1,"o":{"a":0,"k":100,"ix":5}},{"ty":"tr","a":{"a":0,"k":[0,0],"ix":1},"s":{"a":0,"k":[100,100],"ix":3},"sk":{"a":0,"k":0,"ix":4},"p":{"a":0,"k":[0,0],"ix":2},"r":{"a":0,"k":0,"ix":6},"sa":{"a":0,"k":0,"ix":5},"o":{"a":0,"k":100,"ix":7}}]},{"ty":"gr","bm":0,"hd":false,"mn":"ADBE Vector Group","nm":"Group 17","ix":17,"cix":2,"np":2,"it":[{"ty":"sh","bm":0,"hd":false,"mn":"ADBE Vector Shape - Group","nm":"Path 1","ix":1,"d":1,"ks":{"a":0,"k":{"c":true,"i":[[-2.094,-2.894],[-1.304,1.401],[-0.271,0.185],[0,0],[-0.002,0.141],[-0.621,0.422],[0,0],[0,0],[0,0],[0,0],[-0.305,0.208],[0,0],[0,0],[0,0],[0,0],[0,0]],"o":[[-0.689,-2.179],[0.207,-0.227],[0,0],[-0.019,-0.149],[-0.007,-0.907],[0,0],[0,0],[0,0],[0,0],[0.194,-0.275],[0,0],[0,0],[0,0],[0,0],[0,0],[-2.43,1.653]],"v":[[-84.224,91.916],[-83.541,86.247],[-82.823,85.629],[-82.474,85.404],[-82.501,84.972],[-81.589,83.002],[-57.809,67.745],[-56.957,69.045],[-55.951,68.402],[-57.038,66.74],[-56.29,66.006],[-57.154,66.56],[-57.456,66.102],[-82.26,82.009],[-82.263,82.014],[-84.863,83.679]]},"ix":2}},{"ty":"fl","bm":0,"hd":false,"mn":"ADBE Vector Graphic - Fill","nm":"Fill 1","c":{"a":0,"k":[0.7255,0.7255,0.7255],"ix":4},"r":1,"o":{"a":0,"k":100,"ix":5}},{"ty":"tr","a":{"a":0,"k":[0,0],"ix":1},"s":{"a":0,"k":[100,100],"ix":3},"sk":{"a":0,"k":0,"ix":4},"p":{"a":0,"k":[0,0],"ix":2},"r":{"a":0,"k":0,"ix":6},"sa":{"a":0,"k":0,"ix":5},"o":{"a":0,"k":100,"ix":7}}]},{"ty":"gr","bm":0,"hd":false,"mn":"ADBE Vector Group","nm":"Group 18","ix":18,"cix":2,"np":2,"it":[{"ty":"sh","bm":0,"hd":false,"mn":"ADBE Vector Shape - Group","nm":"Path 1","ix":1,"d":1,"ks":{"a":0,"k":{"c":true,"i":[[-2.094,-2.894],[-2.049,1.222],[0,0],[0.936,4.281],[-1.365,0.932],[0,0]],"o":[[2.018,2.793],[0,0],[-2.979,1.779],[-0.38,-1.722],[0,0],[-2.43,1.653]],"v":[[-84.224,91.916],[-77.102,95.54],[-74.544,93.899],[-83.541,86.247],[-82.263,82.014],[-84.863,83.679]]},"ix":2}},{"ty":"fl","bm":0,"hd":false,"mn":"ADBE Vector Graphic - Fill","nm":"Fill 1","c":{"a":0,"k":[0.8392,0.8392,0.8392],"ix":4},"r":1,"o":{"a":0,"k":100,"ix":5}},{"ty":"tr","a":{"a":0,"k":[0,0],"ix":1},"s":{"a":0,"k":[100,100],"ix":3},"sk":{"a":0,"k":0,"ix":4},"p":{"a":0,"k":[0,0],"ix":2},"r":{"a":0,"k":0,"ix":6},"sa":{"a":0,"k":0,"ix":5},"o":{"a":0,"k":100,"ix":7}}]},{"ty":"gr","bm":0,"hd":false,"mn":"ADBE Vector Group","nm":"Group 19","ix":19,"cix":2,"np":2,"it":[{"ty":"sh","bm":0,"hd":false,"mn":"ADBE Vector Shape - Group","nm":"Path 1","ix":1,"d":1,"ks":{"a":0,"k":{"c":true,"i":[[-2.416,-1.588],[-0.87,0.52],[0,0],[0,0],[0,0],[-0.008,-0.903]],"o":[[0.66,0.434],[0,0],[0,0],[0,0],[-0.621,0.424],[0.021,2.322]],"v":[[-77.925,92.311],[-75.156,92.875],[-51.352,77.609],[-57.807,67.744],[-81.59,82.998],[-82.5,84.971]]},"ix":2}},{"ty":"fl","bm":0,"hd":false,"mn":"ADBE Vector Graphic - Fill","nm":"Fill 1","c":{"a":0,"k":[0.7255,0.7255,0.7255],"ix":4},"r":1,"o":{"a":0,"k":100,"ix":5}},{"ty":"tr","a":{"a":0,"k":[0,0],"ix":1},"s":{"a":0,"k":[100,100],"ix":3},"sk":{"a":0,"k":0,"ix":4},"p":{"a":0,"k":[0,0],"ix":2},"r":{"a":0,"k":0,"ix":6},"sa":{"a":0,"k":0,"ix":5},"o":{"a":0,"k":100,"ix":7}}]},{"ty":"gr","bm":0,"hd":false,"mn":"ADBE Vector Group","nm":"Group 20","ix":20,"cix":2,"np":2,"it":[{"ty":"sh","bm":0,"hd":false,"mn":"ADBE Vector Shape - Group","nm":"Path 1","ix":1,"d":1,"ks":{"a":0,"k":{"c":true,"i":[[-0.38,-1.722],[-2.979,1.779],[0,0],[0,0],[0,0],[0,0],[0,0],[0,0],[0,0],[0,0],[0,0]],"o":[[0.936,4.281],[0,0],[0,0],[0,0],[0,0],[0,0],[0,0],[0,0],[0,0],[0,0],[-1.365,0.932]],"v":[[-83.541,86.247],[-74.544,93.899],[-49.695,77.963],[-49.976,77.532],[-50.118,77.315],[-55.951,68.402],[-57.038,66.74],[-57.154,66.56],[-57.456,66.102],[-82.26,82.009],[-82.263,82.014]]},"ix":2}},{"ty":"fl","bm":0,"hd":false,"mn":"ADBE Vector Graphic - Fill","nm":"Fill 1","c":{"a":0,"k":[0.8392,0.8392,0.8392],"ix":4},"r":1,"o":{"a":0,"k":100,"ix":5}},{"ty":"tr","a":{"a":0,"k":[0,0],"ix":1},"s":{"a":0,"k":[100,100],"ix":3},"sk":{"a":0,"k":0,"ix":4},"p":{"a":0,"k":[0,0],"ix":2},"r":{"a":0,"k":0,"ix":6},"sa":{"a":0,"k":0,"ix":5},"o":{"a":0,"k":100,"ix":7}}]},{"ty":"gr","bm":0,"hd":false,"mn":"ADBE Vector Group","nm":"Group 21","ix":21,"cix":2,"np":2,"it":[{"ty":"sh","bm":0,"hd":false,"mn":"ADBE Vector Shape - Group","nm":"Path 1","ix":1,"d":1,"ks":{"a":0,"k":{"c":true,"i":[[-5.362,3.203],[0,0],[-4.066,2.771],[0,0],[0,0],[0,0]],"o":[[0,0],[-4.288,-3.603],[0,0],[0,0],[0,0],[-6.124,4.175]],"v":[[-79.728,99.535],[-79.237,99.222],[-82.823,85.629],[-51.856,65.774],[-54.5,61.733],[-89.697,84.303]]},"ix":2}},{"ty":"fl","bm":0,"hd":false,"mn":"ADBE Vector Graphic - Fill","nm":"Fill 1","c":{"a":0,"k":[0.6745,0.6745,0.6745],"ix":4},"r":1,"o":{"a":0,"k":100,"ix":5}},{"ty":"tr","a":{"a":0,"k":[0,0],"ix":1},"s":{"a":0,"k":[100,100],"ix":3},"sk":{"a":0,"k":0,"ix":4},"p":{"a":0,"k":[0,0],"ix":2},"r":{"a":0,"k":0,"ix":6},"sa":{"a":0,"k":0,"ix":5},"o":{"a":0,"k":100,"ix":7}}]},{"ty":"gr","bm":0,"hd":false,"mn":"ADBE Vector Group","nm":"Group 22","ix":22,"cix":2,"np":2,"it":[{"ty":"sh","bm":0,"hd":false,"mn":"ADBE Vector Shape - Group","nm":"Path 1","ix":1,"d":1,"ks":{"a":0,"k":{"c":true,"i":[[-5.362,3.203],[0,0],[0,0],[0,0]],"o":[[0,0],[0,0],[0,0],[-6.124,4.175]],"v":[[-79.728,99.535],[-44.53,76.965],[-54.5,61.733],[-89.697,84.303]]},"ix":2}},{"ty":"fl","bm":0,"hd":false,"mn":"ADBE Vector Graphic - Fill","nm":"Fill 1","c":{"a":0,"k":[0.7255,0.7255,0.7255],"ix":4},"r":1,"o":{"a":0,"k":100,"ix":5}},{"ty":"tr","a":{"a":0,"k":[0,0],"ix":1},"s":{"a":0,"k":[100,100],"ix":3},"sk":{"a":0,"k":0,"ix":4},"p":{"a":0,"k":[0,0],"ix":2},"r":{"a":0,"k":0,"ix":6},"sa":{"a":0,"k":0,"ix":5},"o":{"a":0,"k":100,"ix":7}}]}],"ind":6,"parent":1},{"ty":4,"nm":"Layer 2","sr":1,"st":0,"op":125,"ip":0,"hd":false,"ddd":0,"bm":0,"hasMask":false,"ao":0,"ks":{"a":{"a":0,"k":[51.775,74.142,0],"ix":1},"s":{"a":0,"k":[100,100,100],"ix":6},"sk":{"a":0,"k":0},"p":{"a":1,"k":[{"o":{"x":0.333,"y":0},"i":{"x":0.407,"y":1},"s":[101.775,124.142,0],"t":0,"ti":[0,0,0],"to":[0,-3.333,0]},{"o":{"x":0.606,"y":0},"i":{"x":0.667,"y":1},"s":[101.775,104.142,0],"t":10,"ti":[0,-3.333,0],"to":[0,0,0]},{"o":{"x":0.167,"y":0.167},"i":{"x":0.833,"y":0.833},"s":[101.775,124.142,0],"t":20,"ti":[0,0,0],"to":[0,0,0]},{"o":{"x":0.167,"y":0.167},"i":{"x":0.833,"y":0.833},"s":[101.775,124.142,0],"t":45,"ti":[5,2.5,0],"to":[-5,-2.5,0]},{"o":{"x":0.167,"y":0.167},"i":{"x":0.833,"y":0.833},"s":[71.775,109.142,0],"t":50,"ti":[0,0,0],"to":[0,0,0]},{"o":{"x":0.167,"y":0.167},"i":{"x":0.667,"y":1},"s":[71.775,109.142,0],"t":55,"ti":[-5,-2.5,0],"to":[5,2.5,0]},{"s":[101.775,124.142,0],"t":66}],"ix":2},"r":{"a":1,"k":[{"o":{"x":0.167,"y":0.167},"i":{"x":0.833,"y":0.833},"s":[45],"t":30},{"o":{"x":0.167,"y":0.167},"i":{"x":0.833,"y":0.833},"s":[65],"t":35},{"o":{"x":0.167,"y":0.167},"i":{"x":0.833,"y":0.833},"s":[11],"t":40},{"o":{"x":0.167,"y":0.167},"i":{"x":0.833,"y":0.833},"s":[9],"t":45},{"o":{"x":0.167,"y":0.167},"i":{"x":0.833,"y":0.833},"s":[4],"t":50},{"o":{"x":0.167,"y":0.167},"i":{"x":0.833,"y":0.833},"s":[40],"t":55},{"o":{"x":0.167,"y":0.167},"i":{"x":0.667,"y":1},"s":[63],"t":60},{"o":{"x":0.333,"y":0},"i":{"x":0.667,"y":1},"s":[45],"t":66},{"o":{"x":0.333,"y":0},"i":{"x":0.667,"y":1},"s":[25],"t":73},{"s":[45],"t":80}],"ix":10},"sa":{"a":0,"k":0},"o":{"a":0,"k":100,"ix":11}},"ef":[],"shapes":[{"ty":"gr","bm":0,"hd":false,"mn":"ADBE Vector Group","nm":"Group 1","ix":1,"cix":2,"np":2,"it":[{"ty":"sh","bm":0,"hd":false,"mn":"ADBE Vector Shape - Group","nm":"Path 1","ix":1,"d":1,"ks":{"a":0,"k":{"c":true,"i":[[0.203,-1.399],[0,0],[1.132,0.774],[0,0]],"o":[[0,0],[0.199,-1.396],[0,0],[1.136,0.771]],"v":[[78.945,83.144],[76.543,81.602],[75.274,78.18],[77.68,79.719]]},"ix":2}},{"ty":"fl","bm":0,"hd":false,"mn":"ADBE Vector Graphic - Fill","nm":"Fill 1","c":{"a":0,"k":[0.7255,0.7255,0.7255],"ix":4},"r":1,"o":{"a":0,"k":100,"ix":5}},{"ty":"tr","a":{"a":0,"k":[0,0],"ix":1},"s":{"a":0,"k":[100,100],"ix":3},"sk":{"a":0,"k":0,"ix":4},"p":{"a":0,"k":[0,0],"ix":2},"r":{"a":0,"k":0,"ix":6},"sa":{"a":0,"k":0,"ix":5},"o":{"a":0,"k":100,"ix":7}}]},{"ty":"gr","bm":0,"hd":false,"mn":"ADBE Vector Group","nm":"Group 2","ix":2,"cix":2,"np":2,"it":[{"ty":"sh","bm":0,"hd":false,"mn":"ADBE Vector Shape - Group","nm":"Path 1","ix":1,"d":1,"ks":{"a":0,"k":{"c":true,"i":[[0,0],[0.199,-1.396],[0,0],[0,0],[1.132,0.774]],"o":[[1.139,0.776],[0,0],[0,0],[0.199,-1.396],[0,0]],"v":[[71.353,75.659],[72.62,79.088],[70.219,77.546],[70.216,77.541],[68.947,74.12]]},"ix":2}},{"ty":"fl","bm":0,"hd":false,"mn":"ADBE Vector Graphic - Fill","nm":"Fill 1","c":{"a":0,"k":[0.7255,0.7255,0.7255],"ix":4},"r":1,"o":{"a":0,"k":100,"ix":5}},{"ty":"tr","a":{"a":0,"k":[0,0],"ix":1},"s":{"a":0,"k":[100,100],"ix":3},"sk":{"a":0,"k":0,"ix":4},"p":{"a":0,"k":[0,0],"ix":2},"r":{"a":0,"k":0,"ix":6},"sa":{"a":0,"k":0,"ix":5},"o":{"a":0,"k":100,"ix":7}}]},{"ty":"gr","bm":0,"hd":false,"mn":"ADBE Vector Group","nm":"Group 3","ix":3,"cix":2,"np":2,"it":[{"ty":"sh","bm":0,"hd":false,"mn":"ADBE Vector Shape - Group","nm":"Path 1","ix":1,"d":1,"ks":{"a":0,"k":{"c":true,"i":[[0,0],[0.203,-1.399],[0,0],[1.132,0.774]],"o":[[1.136,0.771],[0,0],[0.196,-1.4],[0,0]],"v":[[65.024,71.606],[66.288,75.03],[63.887,73.488],[62.619,70.059]]},"ix":2}},{"ty":"fl","bm":0,"hd":false,"mn":"ADBE Vector Graphic - Fill","nm":"Fill 1","c":{"a":0,"k":[0.7255,0.7255,0.7255],"ix":4},"r":1,"o":{"a":0,"k":100,"ix":5}},{"ty":"tr","a":{"a":0,"k":[0,0],"ix":1},"s":{"a":0,"k":[100,100],"ix":3},"sk":{"a":0,"k":0,"ix":4},"p":{"a":0,"k":[0,0],"ix":2},"r":{"a":0,"k":0,"ix":6},"sa":{"a":0,"k":0,"ix":5},"o":{"a":0,"k":100,"ix":7}}]},{"ty":"gr","bm":0,"hd":false,"mn":"ADBE Vector Group","nm":"Group 4","ix":4,"cix":2,"np":2,"it":[{"ty":"sh","bm":0,"hd":false,"mn":"ADBE Vector Shape - Group","nm":"Path 1","ix":1,"d":1,"ks":{"a":0,"k":{"c":true,"i":[[2.937,1.875],[21.437,17.5],[2.438,2.126],[4.313,4.063],[17.875,24.5],[0.687,21],[0,1.625],[0,-0.688],[-6.5,-8.938],[-17.188,-15.75],[-6.125,-4.875],[0,0],[-1.563,4.562]],"o":[[0,0],[-2.312,-1.875],[-4,-3.438],[-16.75,-15.5],[-6.562,-8.938],[-0.063,-2],[0.063,0.625],[0.687,20.999],[18.563,25.312],[7.063,6.499],[20.313,16.312],[2.187,1.437],[2.312,2.5]],"v":[[38.732,71.718],[2.419,45.842],[-4.706,39.905],[-17.206,28.717],[-70.456,-31.157],[-91.456,-81.032],[-91.518,-86.532],[-91.456,-84.532],[-70.456,-34.594],[-15.331,26.905],[4.544,44.03],[38.794,68.218],[47.794,58.155]]},"ix":2}},{"ty":"fl","bm":0,"hd":false,"mn":"ADBE Vector Graphic - Fill","nm":"Fill 1","c":{"a":0,"k":[0.8157,0.8078,0.949],"ix":4},"r":1,"o":{"a":0,"k":100,"ix":5}},{"ty":"tr","a":{"a":0,"k":[0,0],"ix":1},"s":{"a":0,"k":[100,100],"ix":3},"sk":{"a":0,"k":0,"ix":4},"p":{"a":0,"k":[0,0],"ix":2},"r":{"a":0,"k":0,"ix":6},"sa":{"a":0,"k":0,"ix":5},"o":{"a":0,"k":100,"ix":7}}]},{"ty":"gr","bm":0,"hd":false,"mn":"ADBE Vector Group","nm":"Group 5","ix":5,"cix":2,"np":2,"it":[{"ty":"sh","bm":0,"hd":false,"mn":"ADBE Vector Shape - Group","nm":"Path 1","ix":1,"d":1,"ks":{"a":0,"k":{"c":true,"i":[[3,1.937],[21.437,17.5],[6.937,6.5],[17.875,24.5],[0.687,21],[-2.438,-6.313],[-31.062,-31.813],[-6.063,-5.625],[-5.25,-2.875]],"o":[[0,0],[-6.063,-4.937],[-16.75,-15.5],[-6.562,-8.938],[-0.75,-21],[13.937,35.5],[6.75,6.937],[13.875,13.062],[3,1.937]],"v":[[38.732,71.718],[2.419,45.842],[-17.206,28.717],[-70.456,-31.157],[-91.456,-81.032],[-82.831,-96.532],[-2.081,13.906],[17.232,32.905],[47.607,57.968]]},"ix":2}},{"ty":"fl","bm":0,"hd":false,"mn":"ADBE Vector Graphic - Fill","nm":"Fill 1","c":{"a":0,"k":[0.9529,0.9451,0.9882],"ix":4},"r":1,"o":{"a":0,"k":100,"ix":5}},{"ty":"tr","a":{"a":0,"k":[0,0],"ix":1},"s":{"a":0,"k":[100,100],"ix":3},"sk":{"a":0,"k":0,"ix":4},"p":{"a":0,"k":[0,0],"ix":2},"r":{"a":0,"k":0,"ix":6},"sa":{"a":0,"k":0,"ix":5},"o":{"a":0,"k":100,"ix":7}}]},{"ty":"gr","bm":0,"hd":false,"mn":"ADBE Vector Group","nm":"Group 6","ix":6,"cix":2,"np":2,"it":[{"ty":"sh","bm":0,"hd":false,"mn":"ADBE Vector Shape - Group","nm":"Path 1","ix":1,"d":1,"ks":{"a":0,"k":{"c":true,"i":[[3.732,2.596],[-3.732,-2.596]],"o":[[-3.732,-2.596],[3.732,2.596]],"v":[[38.172,73.115],[48.493,57.083]]},"ix":2}},{"ty":"fl","bm":0,"hd":false,"mn":"ADBE Vector Graphic - Fill","nm":"Fill 1","c":{"a":0,"k":[0.6471,0.6471,0.6471],"ix":4},"r":1,"o":{"a":0,"k":100,"ix":5}},{"ty":"tr","a":{"a":0,"k":[0,0],"ix":1},"s":{"a":0,"k":[100,100],"ix":3},"sk":{"a":0,"k":0,"ix":4},"p":{"a":0,"k":[0,0],"ix":2},"r":{"a":0,"k":0,"ix":6},"sa":{"a":0,"k":0,"ix":5},"o":{"a":0,"k":100,"ix":7}}]},{"ty":"gr","bm":0,"hd":false,"mn":"ADBE Vector Group","nm":"Group 7","ix":7,"cix":2,"np":2,"it":[{"ty":"sh","bm":0,"hd":false,"mn":"ADBE Vector Shape - Group","nm":"Path 1","ix":1,"d":1,"ks":{"a":0,"k":{"c":true,"i":[[3.733,2.6],[0,0],[0,0],[-3.334,2.379],[0,0],[0,0],[0,0],[-0.048,-0.033]],"o":[[0,0],[0,0],[0.502,-3.865],[0,0],[0,0],[0,0],[0.052,0.03],[3.73,2.596]],"v":[[41.381,75.234],[38.324,73.208],[40.632,72.534],[48.517,59.846],[48.493,57.085],[51.54,59.105],[51.55,59.111],[51.703,59.205]]},"ix":2}},{"ty":"fl","bm":0,"hd":false,"mn":"ADBE Vector Graphic - Fill","nm":"Fill 1","c":{"a":0,"k":[0.7451,0.7451,0.7451],"ix":4},"r":1,"o":{"a":0,"k":100,"ix":5}},{"ty":"tr","a":{"a":0,"k":[0,0],"ix":1},"s":{"a":0,"k":[100,100],"ix":3},"sk":{"a":0,"k":0,"ix":4},"p":{"a":0,"k":[0,0],"ix":2},"r":{"a":0,"k":0,"ix":6},"sa":{"a":0,"k":0,"ix":5},"o":{"a":0,"k":100,"ix":7}}]},{"ty":"gr","bm":0,"hd":false,"mn":"ADBE Vector Group","nm":"Group 8","ix":8,"cix":2,"np":2,"it":[{"ty":"sh","bm":0,"hd":false,"mn":"ADBE Vector Shape - Group","nm":"Path 1","ix":1,"d":1,"ks":{"a":0,"k":{"c":true,"i":[[4.255,-6.792],[3.928,0.202],[-3.117,4.793],[3.95,2.477],[3.549,-2.773],[-2.919,-1.825]],"o":[[-3.404,5.442],[3.682,-0.35],[4.277,-6.58],[-2.649,-1.652],[3.769,-3.405],[4.042,2.527]],"v":[[53.216,71.97],[40.89,80.507],[52.079,72.303],[52.665,55.9],[42.602,57.953],[53.601,55.084]]},"ix":2}},{"ty":"fl","bm":0,"hd":false,"mn":"ADBE Vector Graphic - Fill","nm":"Fill 1","c":{"a":0,"k":[0.7451,0.7451,0.7451],"ix":4},"r":1,"o":{"a":0,"k":100,"ix":5}},{"ty":"tr","a":{"a":0,"k":[0,0],"ix":1},"s":{"a":0,"k":[100,100],"ix":3},"sk":{"a":0,"k":0,"ix":4},"p":{"a":0,"k":[0,0],"ix":2},"r":{"a":0,"k":0,"ix":6},"sa":{"a":0,"k":0,"ix":5},"o":{"a":0,"k":100,"ix":7}}]},{"ty":"gr","bm":0,"hd":false,"mn":"ADBE Vector Group","nm":"Group 9","ix":9,"cix":2,"np":2,"it":[{"ty":"sh","bm":0,"hd":false,"mn":"ADBE Vector Shape - Group","nm":"Path 1","ix":1,"d":1,"ks":{"a":0,"k":{"c":true,"i":[[-2.09,-1.309],[3.547,-5.924],[2.085,1.305],[-3.11,4.76]],"o":[[2.085,1.305],[-3.418,5.708],[-2.09,-1.309],[3.11,-4.76]],"v":[[52.022,58.517],[50.168,69.504],[40.759,75.755],[42.605,64.769]]},"ix":2}},{"ty":"fl","bm":0,"hd":false,"mn":"ADBE Vector Graphic - Fill","nm":"Fill 1","c":{"a":0,"k":[0.8,0.8,0.8],"ix":4},"r":1,"o":{"a":0,"k":100,"ix":5}},{"ty":"tr","a":{"a":0,"k":[0,0],"ix":1},"s":{"a":0,"k":[100,100],"ix":3},"sk":{"a":0,"k":0,"ix":4},"p":{"a":0,"k":[0,0],"ix":2},"r":{"a":0,"k":0,"ix":6},"sa":{"a":0,"k":0,"ix":5},"o":{"a":0,"k":100,"ix":7}}]},{"ty":"gr","bm":0,"hd":false,"mn":"ADBE Vector Group","nm":"Group 10","ix":10,"cix":2,"np":2,"it":[{"ty":"sh","bm":0,"hd":false,"mn":"ADBE Vector Shape - Group","nm":"Path 1","ix":1,"d":1,"ks":{"a":0,"k":{"c":true,"i":[[-4.048,-2.534],[4.253,-6.795],[4.038,2.528],[-4.253,6.795]],"o":[[4.038,2.528],[-4.253,6.795],[-4.048,-2.534],[4.253,-6.795]],"v":[[53.602,55.085],[53.218,71.972],[38.201,79.69],[38.571,62.803]]},"ix":2}},{"ty":"fl","bm":0,"hd":false,"mn":"ADBE Vector Graphic - Fill","nm":"Fill 1","c":{"a":0,"k":[0.9098,0.9098,0.9098],"ix":4},"r":1,"o":{"a":0,"k":100,"ix":5}},{"ty":"tr","a":{"a":0,"k":[0,0],"ix":1},"s":{"a":0,"k":[100,100],"ix":3},"sk":{"a":0,"k":0,"ix":4},"p":{"a":0,"k":[0,0],"ix":2},"r":{"a":0,"k":0,"ix":6},"sa":{"a":0,"k":0,"ix":5},"o":{"a":0,"k":100,"ix":7}}]},{"ty":"gr","bm":0,"hd":false,"mn":"ADBE Vector Group","nm":"Group 11","ix":11,"cix":2,"np":2,"it":[{"ty":"sh","bm":0,"hd":false,"mn":"ADBE Vector Shape - Group","nm":"Path 1","ix":1,"d":1,"ks":{"a":0,"k":{"c":true,"i":[[-0.295,-0.656],[-0.003,-0.005],[3.261,-5.205],[3.947,0.094],[1.638,2.699],[-0.453,-0.137],[-3.132,4.997],[-3.856,0.075],[0.135,0.443],[-1.36,-1.525]],"o":[[0.008,0.002],[1.59,3.496],[-3.433,5.487],[-2.597,-0.062],[0.481,0.06],[-1.351,-3.517],[3.268,-5.223],[-0.194,-0.385],[1.804,0.346],[0.452,0.507]],"v":[[57.645,58.958],[57.657,58.977],[55.131,73.333],[42.711,81.866],[36.387,77.802],[37.787,78.095],[40.484,64.166],[52.331,55.62],[51.835,54.382],[56.49,57.24]]},"ix":2}},{"ty":"fl","bm":0,"hd":false,"mn":"ADBE Vector Graphic - Fill","nm":"Fill 1","c":{"a":0,"k":[0.8,0.8,0.8],"ix":4},"r":1,"o":{"a":0,"k":100,"ix":5}},{"ty":"tr","a":{"a":0,"k":[0,0],"ix":1},"s":{"a":0,"k":[100,100],"ix":3},"sk":{"a":0,"k":0,"ix":4},"p":{"a":0,"k":[0,0],"ix":2},"r":{"a":0,"k":0,"ix":6},"sa":{"a":0,"k":0,"ix":5},"o":{"a":0,"k":100,"ix":7}}]},{"ty":"gr","bm":0,"hd":false,"mn":"ADBE Vector Group","nm":"Group 12","ix":12,"cix":2,"np":2,"it":[{"ty":"sh","bm":0,"hd":false,"mn":"ADBE Vector Shape - Group","nm":"Path 1","ix":1,"d":1,"ks":{"a":0,"k":{"c":true,"i":[[0.203,-1.399],[0,0],[0.526,0.731],[0.305,0.208],[0,0],[0,0]],"o":[[0,0],[0.14,-1.02],[-0.194,-0.275],[0,0],[0,0],[1.136,0.771]],"v":[[59.961,70.969],[57.562,69.432],[57.038,66.74],[56.29,66.006],[57.154,66.56],[58.696,67.545]]},"ix":2}},{"ty":"fl","bm":0,"hd":false,"mn":"ADBE Vector Graphic - Fill","nm":"Fill 1","c":{"a":0,"k":[0.7255,0.7255,0.7255],"ix":4},"r":1,"o":{"a":0,"k":100,"ix":5}},{"ty":"tr","a":{"a":0,"k":[0,0],"ix":1},"s":{"a":0,"k":[100,100],"ix":3},"sk":{"a":0,"k":0,"ix":4},"p":{"a":0,"k":[0,0],"ix":2},"r":{"a":0,"k":0,"ix":6},"sa":{"a":0,"k":0,"ix":5},"o":{"a":0,"k":100,"ix":7}}]},{"ty":"gr","bm":0,"hd":false,"mn":"ADBE Vector Group","nm":"Group 13","ix":13,"cix":2,"np":2,"it":[{"ty":"sh","bm":0,"hd":false,"mn":"ADBE Vector Shape - Group","nm":"Path 1","ix":1,"d":1,"ks":{"a":0,"k":{"c":true,"i":[[0.203,-1.399],[2.871,1.713],[0,0],[0,0],[-0.343,-0.028],[-0.505,3.614],[0.526,0.731],[0.305,0.208],[0,0],[0,0]],"o":[[-0.572,4.035],[0,0],[0,0],[0.307,0.181],[2.907,0.308],[0.14,-1.02],[-0.194,-0.275],[0,0],[0,0],[1.136,0.771]],"v":[[59.961,70.969],[51.513,78.519],[49.976,77.532],[49.146,77],[50.118,77.315],[57.562,69.432],[57.038,66.74],[56.29,66.006],[57.154,66.56],[58.696,67.545]]},"ix":2}},{"ty":"fl","bm":0,"hd":false,"mn":"ADBE Vector Graphic - Fill","nm":"Fill 1","c":{"a":0,"k":[0.8392,0.8392,0.8392],"ix":4},"r":1,"o":{"a":0,"k":100,"ix":5}},{"ty":"tr","a":{"a":0,"k":[0,0],"ix":1},"s":{"a":0,"k":[100,100],"ix":3},"sk":{"a":0,"k":0,"ix":4},"p":{"a":0,"k":[0,0],"ix":2},"r":{"a":0,"k":0,"ix":6},"sa":{"a":0,"k":0,"ix":5},"o":{"a":0,"k":100,"ix":7}}]},{"ty":"gr","bm":0,"hd":false,"mn":"ADBE Vector Group","nm":"Group 14","ix":14,"cix":2,"np":2,"it":[{"ty":"sh","bm":0,"hd":false,"mn":"ADBE Vector Shape - Group","nm":"Path 1","ix":1,"d":1,"ks":{"a":0,"k":{"c":true,"i":[[0.203,-1.399],[2.864,1.712],[0,0],[-0.554,4.043],[1.132,0.774],[0,0]],"o":[[-0.575,4.03],[0,0],[2.87,1.721],[0.196,-1.4],[0,0],[1.136,0.771]],"v":[[66.288,75.03],[57.846,82.577],[55.478,81.058],[63.887,73.488],[62.619,70.059],[65.024,71.606]]},"ix":2}},{"ty":"fl","bm":0,"hd":false,"mn":"ADBE Vector Graphic - Fill","nm":"Fill 1","c":{"a":0,"k":[0.8392,0.8392,0.8392],"ix":4},"r":1,"o":{"a":0,"k":100,"ix":5}},{"ty":"tr","a":{"a":0,"k":[0,0],"ix":1},"s":{"a":0,"k":[100,100],"ix":3},"sk":{"a":0,"k":0,"ix":4},"p":{"a":0,"k":[0,0],"ix":2},"r":{"a":0,"k":0,"ix":6},"sa":{"a":0,"k":0,"ix":5},"o":{"a":0,"k":100,"ix":7}}]},{"ty":"gr","bm":0,"hd":false,"mn":"ADBE Vector Group","nm":"Group 15","ix":15,"cix":2,"np":2,"it":[{"ty":"sh","bm":0,"hd":false,"mn":"ADBE Vector Shape - Group","nm":"Path 1","ix":1,"d":1,"ks":{"a":0,"k":{"c":true,"i":[[0.199,-1.396],[2.868,1.709],[0,0],[-0.559,4.046],[0,0],[1.132,0.774],[0,0]],"o":[[-0.58,4.033],[0,0],[2.871,1.713],[0,0],[0.199,-1.396],[0,0],[1.139,0.776]],"v":[[72.62,79.088],[64.173,86.638],[61.806,85.118],[70.219,77.546],[70.216,77.541],[68.947,74.12],[71.353,75.659]]},"ix":2}},{"ty":"fl","bm":0,"hd":false,"mn":"ADBE Vector Graphic - Fill","nm":"Fill 1","c":{"a":0,"k":[0.8392,0.8392,0.8392],"ix":4},"r":1,"o":{"a":0,"k":100,"ix":5}},{"ty":"tr","a":{"a":0,"k":[0,0],"ix":1},"s":{"a":0,"k":[100,100],"ix":3},"sk":{"a":0,"k":0,"ix":4},"p":{"a":0,"k":[0,0],"ix":2},"r":{"a":0,"k":0,"ix":6},"sa":{"a":0,"k":0,"ix":5},"o":{"a":0,"k":100,"ix":7}}]},{"ty":"gr","bm":0,"hd":false,"mn":"ADBE Vector Group","nm":"Group 16","ix":16,"cix":2,"np":2,"it":[{"ty":"sh","bm":0,"hd":false,"mn":"ADBE Vector Shape - Group","nm":"Path 1","ix":1,"d":1,"ks":{"a":0,"k":{"c":true,"i":[[0.203,-1.399],[2.871,1.713],[0,0],[-0.554,4.043],[1.132,0.774],[0,0]],"o":[[-0.568,4.032],[0,0],[2.871,1.713],[0.199,-1.396],[0,0],[1.136,0.771]],"v":[[78.945,83.144],[70.498,90.694],[68.134,89.179],[76.543,81.602],[75.274,78.18],[77.68,79.719]]},"ix":2}},{"ty":"fl","bm":0,"hd":false,"mn":"ADBE Vector Graphic - Fill","nm":"Fill 1","c":{"a":0,"k":[0.8392,0.8392,0.8392],"ix":4},"r":1,"o":{"a":0,"k":100,"ix":5}},{"ty":"tr","a":{"a":0,"k":[0,0],"ix":1},"s":{"a":0,"k":[100,100],"ix":3},"sk":{"a":0,"k":0,"ix":4},"p":{"a":0,"k":[0,0],"ix":2},"r":{"a":0,"k":0,"ix":6},"sa":{"a":0,"k":0,"ix":5},"o":{"a":0,"k":100,"ix":7}}]},{"ty":"gr","bm":0,"hd":false,"mn":"ADBE Vector Group","nm":"Group 17","ix":17,"cix":2,"np":2,"it":[{"ty":"sh","bm":0,"hd":false,"mn":"ADBE Vector Shape - Group","nm":"Path 1","ix":1,"d":1,"ks":{"a":0,"k":{"c":true,"i":[[2.094,-2.894],[1.304,1.401],[0.271,0.185],[0,0],[0.002,0.141],[0.621,0.422],[0,0],[0,0],[0,0],[0,0],[0.305,0.208],[0,0],[0,0],[0,0],[0,0],[0,0]],"o":[[0.689,-2.179],[-0.207,-0.227],[0,0],[0.019,-0.149],[0.007,-0.907],[0,0],[0,0],[0,0],[0,0],[-0.194,-0.275],[0,0],[0,0],[0,0],[0,0],[0,0],[2.43,1.653]],"v":[[84.224,91.916],[83.541,86.247],[82.823,85.629],[82.474,85.404],[82.501,84.972],[81.589,83.002],[57.809,67.745],[56.957,69.045],[55.951,68.402],[57.038,66.74],[56.29,66.006],[57.154,66.56],[57.456,66.102],[82.26,82.009],[82.263,82.014],[84.863,83.679]]},"ix":2}},{"ty":"fl","bm":0,"hd":false,"mn":"ADBE Vector Graphic - Fill","nm":"Fill 1","c":{"a":0,"k":[0.7255,0.7255,0.7255],"ix":4},"r":1,"o":{"a":0,"k":100,"ix":5}},{"ty":"tr","a":{"a":0,"k":[0,0],"ix":1},"s":{"a":0,"k":[100,100],"ix":3},"sk":{"a":0,"k":0,"ix":4},"p":{"a":0,"k":[0,0],"ix":2},"r":{"a":0,"k":0,"ix":6},"sa":{"a":0,"k":0,"ix":5},"o":{"a":0,"k":100,"ix":7}}]},{"ty":"gr","bm":0,"hd":false,"mn":"ADBE Vector Group","nm":"Group 18","ix":18,"cix":2,"np":2,"it":[{"ty":"sh","bm":0,"hd":false,"mn":"ADBE Vector Shape - Group","nm":"Path 1","ix":1,"d":1,"ks":{"a":0,"k":{"c":true,"i":[[2.094,-2.894],[2.049,1.222],[0,0],[-0.936,4.281],[1.365,0.932],[0,0]],"o":[[-2.018,2.793],[0,0],[2.979,1.779],[0.38,-1.722],[0,0],[2.43,1.653]],"v":[[84.224,91.916],[77.102,95.54],[74.544,93.899],[83.541,86.247],[82.263,82.014],[84.863,83.679]]},"ix":2}},{"ty":"fl","bm":0,"hd":false,"mn":"ADBE Vector Graphic - Fill","nm":"Fill 1","c":{"a":0,"k":[0.8392,0.8392,0.8392],"ix":4},"r":1,"o":{"a":0,"k":100,"ix":5}},{"ty":"tr","a":{"a":0,"k":[0,0],"ix":1},"s":{"a":0,"k":[100,100],"ix":3},"sk":{"a":0,"k":0,"ix":4},"p":{"a":0,"k":[0,0],"ix":2},"r":{"a":0,"k":0,"ix":6},"sa":{"a":0,"k":0,"ix":5},"o":{"a":0,"k":100,"ix":7}}]},{"ty":"gr","bm":0,"hd":false,"mn":"ADBE Vector Group","nm":"Group 19","ix":19,"cix":2,"np":2,"it":[{"ty":"sh","bm":0,"hd":false,"mn":"ADBE Vector Shape - Group","nm":"Path 1","ix":1,"d":1,"ks":{"a":0,"k":{"c":true,"i":[[2.416,-1.588],[0.87,0.52],[0,0],[0,0],[0,0],[0.008,-0.903]],"o":[[-0.66,0.434],[0,0],[0,0],[0,0],[0.621,0.424],[-0.021,2.322]],"v":[[77.925,92.311],[75.156,92.875],[51.352,77.609],[57.807,67.744],[81.59,82.998],[82.5,84.971]]},"ix":2}},{"ty":"fl","bm":0,"hd":false,"mn":"ADBE Vector Graphic - Fill","nm":"Fill 1","c":{"a":0,"k":[0.7255,0.7255,0.7255],"ix":4},"r":1,"o":{"a":0,"k":100,"ix":5}},{"ty":"tr","a":{"a":0,"k":[0,0],"ix":1},"s":{"a":0,"k":[100,100],"ix":3},"sk":{"a":0,"k":0,"ix":4},"p":{"a":0,"k":[0,0],"ix":2},"r":{"a":0,"k":0,"ix":6},"sa":{"a":0,"k":0,"ix":5},"o":{"a":0,"k":100,"ix":7}}]},{"ty":"gr","bm":0,"hd":false,"mn":"ADBE Vector Group","nm":"Group 20","ix":20,"cix":2,"np":2,"it":[{"ty":"sh","bm":0,"hd":false,"mn":"ADBE Vector Shape - Group","nm":"Path 1","ix":1,"d":1,"ks":{"a":0,"k":{"c":true,"i":[[0.38,-1.722],[2.979,1.779],[0,0],[0,0],[0,0],[0,0],[0,0],[0,0],[0,0],[0,0],[0,0]],"o":[[-0.936,4.281],[0,0],[0,0],[0,0],[0,0],[0,0],[0,0],[0,0],[0,0],[0,0],[1.365,0.932]],"v":[[83.541,86.247],[74.544,93.899],[49.695,77.963],[49.976,77.532],[50.118,77.315],[55.951,68.402],[57.038,66.74],[57.154,66.56],[57.456,66.102],[82.26,82.009],[82.263,82.014]]},"ix":2}},{"ty":"fl","bm":0,"hd":false,"mn":"ADBE Vector Graphic - Fill","nm":"Fill 1","c":{"a":0,"k":[0.8392,0.8392,0.8392],"ix":4},"r":1,"o":{"a":0,"k":100,"ix":5}},{"ty":"tr","a":{"a":0,"k":[0,0],"ix":1},"s":{"a":0,"k":[100,100],"ix":3},"sk":{"a":0,"k":0,"ix":4},"p":{"a":0,"k":[0,0],"ix":2},"r":{"a":0,"k":0,"ix":6},"sa":{"a":0,"k":0,"ix":5},"o":{"a":0,"k":100,"ix":7}}]},{"ty":"gr","bm":0,"hd":false,"mn":"ADBE Vector Group","nm":"Group 21","ix":21,"cix":2,"np":2,"it":[{"ty":"sh","bm":0,"hd":false,"mn":"ADBE Vector Shape - Group","nm":"Path 1","ix":1,"d":1,"ks":{"a":0,"k":{"c":true,"i":[[5.362,3.203],[0,0],[4.066,2.771],[0,0],[0,0],[0,0]],"o":[[0,0],[4.288,-3.603],[0,0],[0,0],[0,0],[6.124,4.175]],"v":[[79.728,99.535],[79.237,99.222],[82.823,85.629],[51.856,65.774],[54.5,61.733],[89.697,84.303]]},"ix":2}},{"ty":"fl","bm":0,"hd":false,"mn":"ADBE Vector Graphic - Fill","nm":"Fill 1","c":{"a":0,"k":[0.6745,0.6745,0.6745],"ix":4},"r":1,"o":{"a":0,"k":100,"ix":5}},{"ty":"tr","a":{"a":0,"k":[0,0],"ix":1},"s":{"a":0,"k":[100,100],"ix":3},"sk":{"a":0,"k":0,"ix":4},"p":{"a":0,"k":[0,0],"ix":2},"r":{"a":0,"k":0,"ix":6},"sa":{"a":0,"k":0,"ix":5},"o":{"a":0,"k":100,"ix":7}}]},{"ty":"gr","bm":0,"hd":false,"mn":"ADBE Vector Group","nm":"Group 22","ix":22,"cix":2,"np":2,"it":[{"ty":"sh","bm":0,"hd":false,"mn":"ADBE Vector Shape - Group","nm":"Path 1","ix":1,"d":1,"ks":{"a":0,"k":{"c":true,"i":[[5.362,3.203],[0,0],[0,0],[0,0]],"o":[[0,0],[0,0],[0,0],[6.124,4.175]],"v":[[79.728,99.535],[44.53,76.965],[54.5,61.733],[89.697,84.303]]},"ix":2}},{"ty":"fl","bm":0,"hd":false,"mn":"ADBE Vector Graphic - Fill","nm":"Fill 1","c":{"a":0,"k":[0.7255,0.7255,0.7255],"ix":4},"r":1,"o":{"a":0,"k":100,"ix":5}},{"ty":"tr","a":{"a":0,"k":[0,0],"ix":1},"s":{"a":0,"k":[100,100],"ix":3},"sk":{"a":0,"k":0,"ix":4},"p":{"a":0,"k":[0,0],"ix":2},"r":{"a":0,"k":0,"ix":6},"sa":{"a":0,"k":0,"ix":5},"o":{"a":0,"k":100,"ix":7}}]}],"ind":7,"parent":1}],"v":"5.7.11","fr":25,"op":86,"ip":0,"assets":[]}